[
  {
    "file_date": "2019-01-16",
    "end_date": "2018-12-31",
    "shares": 9.6e-05,
    "value": 117,
    "done": true
  },
  {
    "file_date": "2019-01-23",
    "end_date": "2018-12-31",
    "shares": 0.0052,
    "value": 6317,
    "done": true
  },
  {
    "file_date": "2019-01-31",
    "end_date": "2018-12-31",
    "shares": 0.030544,
    "value": 37105,
    "done": true
  },
  {
    "file_date": "2019-02-01",
    "end_date": "2018-12-31",
    "shares": 0.100056,
    "value": 121548,
    "done": true
  },
  {
    "file_date": "2019-02-06",
    "end_date": "2018-12-31",
    "shares": 0.783372,
    "value": 951640,
    "done": true
  },
  {
    "file_date": "2019-02-07",
    "end_date": "2018-12-31",
    "shares": 0.867007,
    "value": 1053240,
    "done": true
  },
  {
    "file_date": "2019-02-08",
    "end_date": "2018-12-31",
    "shares": 2.728078,
    "value": 3314069,
    "done": true
  },
  {
    "file_date": "2019-02-11",
    "end_date": "2018-12-31",
    "shares": 3.139956,
    "value": 3814418,
    "done": true
  },
  {
    "file_date": "2019-02-12",
    "end_date": "2018-12-31",
    "shares": 4.120972,
    "value": 5006157,
    "done": true
  },
  {
    "file_date": "2019-02-13",
    "end_date": "2018-12-31",
    "shares": 9.997087,
    "value": 12144461,
    "done": true
  },
  {
    "file_date": "2019-02-14",
    "end_date": "2018-12-31",
    "shares": 44.820738,
    "value": 54448233,
    "done": true
  },
  {
    "file_date": "2019-02-15",
    "end_date": "2018-12-31",
    "shares": 44.944288,
    "value": 54598321,
    "done": true
  },
  {
    "file_date": "2019-02-27",
    "end_date": "2018-12-31",
    "shares": 51.267249,
    "value": 62279454,
    "done": true
  },
  {
    "file_date": "2019-03-04",
    "end_date": "2018-12-31",
    "shares": 51.596521,
    "value": 62679454,
    "done": true
  },
  {
    "file_date": "2019-03-06",
    "end_date": "2018-12-31",
    "shares": 51.596521,
    "value": 62679454,
    "done": true
  },
  {
    "file_date": "2019-04-01",
    "end_date": "2018-12-31",
    "shares": 51.596521,
    "value": 62679454,
    "done": true
  },
  {
    "file_date": "2019-04-09",
    "end_date": "2019-03-31",
    "shares": 51.60393,
    "value": 62688454,
    "done": true
  },
  {
    "file_date": "2019-04-11",
    "end_date": "2018-12-31",
    "shares": 51.60393,
    "value": 62688454,
    "done": true
  },
  {
    "file_date": "2019-04-15",
    "end_date": "2019-03-31",
    "shares": 51.604074,
    "value": 62688629,
    "done": true
  },
  {
    "file_date": "2019-04-18",
    "end_date": "2019-03-31",
    "shares": 51.609168,
    "value": 62694817,
    "done": true
  },
  {
    "file_date": "2019-04-19",
    "end_date": "2019-03-31",
    "shares": 51.609168,
    "value": 62694817,
    "done": true
  },
  {
    "file_date": "2019-04-24",
    "end_date": "2019-03-31",
    "shares": 51.613119,
    "value": 62699617,
    "done": true
  },
  {
    "file_date": "2019-04-30",
    "end_date": "2019-03-31",
    "shares": 51.623479,
    "value": 62712202,
    "done": true
  },
  {
    "file_date": "2019-05-01",
    "end_date": "2019-03-31",
    "shares": 51.624147,
    "value": 62713014,
    "done": true
  },
  {
    "file_date": "2019-05-02",
    "end_date": "2019-03-31",
    "shares": 51.624304,
    "value": 62713204,
    "done": true
  },
  {
    "file_date": "2019-05-03",
    "end_date": "2019-03-31",
    "shares": 51.624304,
    "value": 62713204,
    "done": true
  },
  {
    "file_date": "2019-05-06",
    "end_date": "2019-03-31",
    "shares": 51.638272,
    "value": 62730173,
    "done": true
  },
  {
    "file_date": "2019-05-07",
    "end_date": "2019-03-31",
    "shares": 51.929103,
    "value": 63083474,
    "done": true
  },
  {
    "file_date": "2019-05-08",
    "end_date": "2019-03-31",
    "shares": 51.897779,
    "value": 63076560,
    "done": true
  },
  {
    "file_date": "2019-05-09",
    "end_date": "2019-03-31",
    "shares": 52.034551,
    "value": 63242793,
    "done": true
  },
  {
    "file_date": "2019-05-10",
    "end_date": "2019-03-31",
    "shares": 51.988086,
    "value": 63186320,
    "done": true
  },
  {
    "file_date": "2019-05-13",
    "end_date": "2019-03-31",
    "shares": 53.059337,
    "value": 64488318,
    "done": true
  },
  {
    "file_date": "2019-05-14",
    "end_date": "2019-03-31",
    "shares": 53.494171,
    "value": 65016816,
    "done": true
  },
  {
    "file_date": "2019-05-15",
    "end_date": "2019-03-31",
    "shares": 54.677881,
    "value": 66455497,
    "done": true
  },
  {
    "file_date": "2019-05-16",
    "end_date": "2019-03-31",
    "shares": 54.677881,
    "value": 66455497,
    "done": true
  },
  {
    "file_date": "2019-05-17",
    "end_date": "2019-03-31",
    "shares": 54.677848,
    "value": 66455456,
    "done": true
  },
  {
    "file_date": "2019-05-22",
    "end_date": "2019-03-31",
    "shares": 54.677848,
    "value": 66455456,
    "done": true
  },
  {
    "file_date": "2019-06-19",
    "end_date": "2019-03-31",
    "shares": 54.677848,
    "value": 66455456,
    "done": true
  },
  {
    "file_date": "2019-07-10",
    "end_date": "2019-06-30",
    "shares": 53.199481,
    "value": 64658649,
    "done": true
  },
  {
    "file_date": "2019-07-18",
    "end_date": "2019-06-30",
    "shares": 53.200304,
    "value": 64659649,
    "done": true
  },
  {
    "file_date": "2019-07-19",
    "end_date": "2019-06-30",
    "shares": 53.253506,
    "value": 64724311,
    "done": true
  },
  {
    "file_date": "2019-07-22",
    "end_date": "2019-06-30",
    "shares": 53.255563,
    "value": 64726811,
    "done": true
  },
  {
    "file_date": "2019-07-25",
    "end_date": "2019-06-30",
    "shares": 53.24866,
    "value": 64718421,
    "done": true
  },
  {
    "file_date": "2019-07-26",
    "end_date": "2019-06-30",
    "shares": 53.243601,
    "value": 64712273,
    "done": true
  },
  {
    "file_date": "2019-07-30",
    "end_date": "2019-06-30",
    "shares": 53.248412,
    "value": 64718120,
    "done": true
  },
  {
    "file_date": "2019-07-31",
    "end_date": "2019-06-30",
    "shares": 53.250935,
    "value": 64721187,
    "done": true
  },
  {
    "file_date": "2019-08-01",
    "end_date": "2019-06-30",
    "shares": 53.277455,
    "value": 64753419,
    "done": true
  },
  {
    "file_date": "2019-08-02",
    "end_date": "2019-06-30",
    "shares": 53.314706,
    "value": 64798694,
    "done": true
  },
  {
    "file_date": "2019-08-05",
    "end_date": "2019-06-30",
    "shares": 53.321696,
    "value": 64807189,
    "done": true
  },
  {
    "file_date": "2019-08-06",
    "end_date": "2019-06-30",
    "shares": 53.309663,
    "value": 64792564,
    "done": true
  },
  {
    "file_date": "2019-08-07",
    "end_date": "2019-06-30",
    "shares": 53.998787,
    "value": 65630126,
    "done": true
  },
  {
    "file_date": "2019-08-08",
    "end_date": "2019-06-30",
    "shares": 53.909072,
    "value": 65634295,
    "done": true
  },
  {
    "file_date": "2019-08-09",
    "end_date": "2019-06-30",
    "shares": 53.820901,
    "value": 65526947,
    "done": true
  },
  {
    "file_date": "2019-08-12",
    "end_date": "2019-06-30",
    "shares": 53.999342,
    "value": 65744199,
    "done": true
  },
  {
    "file_date": "2019-08-13",
    "end_date": "2019-06-30",
    "shares": 54.87127,
    "value": 66805771,
    "done": true
  },
  {
    "file_date": "2019-08-14",
    "end_date": "2019-06-30",
    "shares": 58.862365,
    "value": 71664929,
    "done": true
  },
  {
    "file_date": "2019-08-15",
    "end_date": "2019-06-30",
    "shares": 59.340617,
    "value": 72247201,
    "done": true
  },
  {
    "file_date": "2019-08-16",
    "end_date": "2019-06-30",
    "shares": 59.374852,
    "value": 72288882,
    "done": true
  },
  {
    "file_date": "2019-08-23",
    "end_date": "2019-06-30",
    "shares": 59.374852,
    "value": 72288882,
    "done": true
  },
  {
    "file_date": "2019-09-24",
    "end_date": "2019-06-30",
    "shares": 57.953107,
    "value": 70557908.0,
    "done": true
  },
  {
    "file_date": "2019-10-15",
    "end_date": "2019-09-30",
    "shares": 56.477292,
    "value": 68761103.0,
    "done": true
  },
  {
    "file_date": "2019-10-18",
    "end_date": "2019-09-30",
    "shares": 56.477292,
    "value": 68761103.0,
    "done": true
  },
  {
    "file_date": "2019-10-22",
    "end_date": "2019-09-30",
    "shares": 56.477348,
    "value": 68761171.0,
    "done": true
  },
  {
    "file_date": "2019-10-23",
    "end_date": "2019-09-30",
    "shares": 56.477445,
    "value": 68761289.0,
    "done": true
  },
  {
    "file_date": "2019-10-28",
    "end_date": "2019-09-30",
    "shares": 56.477938,
    "value": 68761889.0,
    "done": true
  },
  {
    "file_date": "2019-10-29",
    "end_date": "2019-09-30",
    "shares": 56.471038,
    "value": 68753489.0,
    "done": true
  },
  {
    "file_date": "2019-10-31",
    "end_date": "2019-09-30",
    "shares": 56.542884,
    "value": 68840961.0,
    "done": true
  },
  {
    "file_date": "2019-11-01",
    "end_date": "2019-09-30",
    "shares": 56.573731,
    "value": 68878517.0,
    "done": true
  },
  {
    "file_date": "2019-11-04",
    "end_date": "2019-09-30",
    "shares": 56.605246,
    "value": 68916887.0,
    "done": true
  },
  {
    "file_date": "2019-11-05",
    "end_date": "2019-09-30",
    "shares": 56.607549,
    "value": 68919691.0,
    "done": true
  },
  {
    "file_date": "2019-11-06",
    "end_date": "2019-06-30",
    "shares": 54.535025,
    "value": 66478196.0,
    "done": true
  },
  {
    "file_date": "2019-11-07",
    "end_date": "2019-09-30",
    "shares": 54.551827,
    "value": 66498677.0,
    "done": true
  },
  {
    "file_date": "2019-11-08",
    "end_date": "2019-09-30",
    "shares": 54.761532,
    "value": 66754308.0,
    "done": true
  },
  {
    "file_date": "2019-11-12",
    "end_date": "2019-09-30",
    "shares": 55.030982,
    "value": 67082767.0,
    "done": true
  },
  {
    "file_date": "2019-11-13",
    "end_date": "2019-09-30",
    "shares": 55.113465,
    "value": 67183314.0,
    "done": true
  },
  {
    "file_date": "2019-11-14",
    "end_date": "2019-09-30",
    "shares": 55.765474,
    "value": 67978113.0,
    "done": true
  },
  {
    "file_date": "2019-11-15",
    "end_date": "2019-09-30",
    "shares": 55.766198,
    "value": 67978995.0,
    "done": true
  },
  {
    "file_date": "2019-11-20",
    "end_date": "2019-09-30",
    "shares": 55.773603,
    "value": 67988022.0,
    "done": true
  },
  {
    "file_date": "2019-11-26",
    "end_date": "2019-09-30",
    "shares": 55.773603,
    "value": 67988022.0,
    "done": true
  },
  {
    "file_date": "2020-01-08",
    "end_date": "2019-12-31",
    "shares": 54.790937,
    "value": 66790152.0,
    "done": true
  },
  {
    "file_date": "2020-01-17",
    "end_date": "2019-12-31",
    "shares": 54.790937,
    "value": 66790152.0,
    "done": true
  },
  {
    "file_date": "2020-01-21",
    "end_date": "2019-12-31",
    "shares": 54.790937,
    "value": 66790152.0,
    "done": true
  },
  {
    "file_date": "2020-01-27",
    "end_date": "2019-12-31",
    "shares": 54.793913,
    "value": 66793780.0,
    "done": true
  },
  {
    "file_date": "2020-01-28",
    "end_date": "2019-12-31",
    "shares": 54.781589,
    "value": 66778757.0,
    "done": true
  },
  {
    "file_date": "2020-01-29",
    "end_date": "2019-12-31",
    "shares": 54.800877,
    "value": 66802269.0,
    "done": true
  },
  {
    "file_date": "2020-01-30",
    "end_date": "2019-12-31",
    "shares": 54.800877,
    "value": 66802269.0,
    "done": true
  },
  {
    "file_date": "2020-01-31",
    "end_date": "2019-12-31",
    "shares": 54.801441,
    "value": 66802957.0,
    "done": true
  },
  {
    "file_date": "2020-02-03",
    "end_date": "2019-12-31",
    "shares": 54.802147,
    "value": 66803817.0,
    "done": true
  },
  {
    "file_date": "2020-02-04",
    "end_date": "2019-12-31",
    "shares": 54.857639,
    "value": 66871462.0,
    "done": true
  },
  {
    "file_date": "2020-02-05",
    "end_date": "2019-12-31",
    "shares": 54.869471,
    "value": 66885885.0,
    "done": true
  },
  {
    "file_date": "2020-02-06",
    "end_date": "2019-12-31",
    "shares": 55.147078,
    "value": 67224288.0,
    "done": true
  },
  {
    "file_date": "2020-02-07",
    "end_date": "2019-12-31",
    "shares": 54.59761,
    "value": 66554486.0,
    "done": true
  },
  {
    "file_date": "2020-02-10",
    "end_date": "2019-12-31",
    "shares": 56.366429,
    "value": 68710677.0,
    "done": true
  },
  {
    "file_date": "2020-02-11",
    "end_date": "2019-12-31",
    "shares": 56.566935,
    "value": 68955094.0,
    "done": true
  },
  {
    "file_date": "2020-02-12",
    "end_date": "2019-12-31",
    "shares": 56.561508,
    "value": 68948478.0,
    "done": true
  },
  {
    "file_date": "2020-02-13",
    "end_date": "2019-12-31",
    "shares": 57.577601,
    "value": 70187096.0,
    "done": true
  },
  {
    "file_date": "2020-02-14",
    "end_date": "2019-12-31",
    "shares": 57.251573,
    "value": 69789667.0,
    "done": true
  },
  {
    "file_date": "2020-02-18",
    "end_date": "2019-12-31",
    "shares": 58.180811,
    "value": 70922409.0,
    "done": true
  },
  {
    "file_date": "2020-02-19",
    "end_date": "2019-12-31",
    "shares": 58.180811,
    "value": 70922409.0,
    "done": true
  },
  {
    "file_date": "2020-02-20",
    "end_date": "2019-12-31",
    "shares": 58.180811,
    "value": 70922409.0,
    "done": true
  },
  {
    "file_date": "2020-02-28",
    "end_date": "2019-12-31",
    "shares": 56.778808,
    "value": 70922409.0,
    "done": true
  },
  {
    "file_date": "2020-03-03",
    "end_date": "2019-12-31",
    "shares": 57.631086,
    "value": 71986989.0,
    "done": true
  },
  {
    "file_date": "2020-03-06",
    "end_date": "2019-12-31",
    "shares": 57.626562,
    "value": 71981339.0,
    "done": true
  },
  {
    "file_date": "2020-03-11",
    "end_date": "2019-12-31",
    "shares": 57.626562,
    "value": 71981339.0,
    "done": true
  },
  {
    "file_date": "2020-03-18",
    "end_date": "2019-12-31",
    "shares": 57.626562,
    "value": 71981339.0,
    "done": true
  },
  {
    "file_date": "2020-04-09",
    "end_date": "2020-03-31",
    "shares": 57.7449,
    "value": 72129155.0,
    "done": true
  },
  {
    "file_date": "2020-04-10",
    "end_date": "2020-03-31",
    "shares": 57.265407,
    "value": 71530220.0,
    "done": true
  },
  {
    "file_date": "2020-04-13",
    "end_date": "2020-03-31",
    "shares": 57.265434,
    "value": 71530253.0,
    "done": true
  },
  {
    "file_date": "2020-04-17",
    "end_date": "2020-03-31",
    "shares": 57.266754,
    "value": 71531903.0,
    "done": true
  },
  {
    "file_date": "2020-04-23",
    "end_date": "2020-03-31",
    "shares": 57.26686,
    "value": 71532035.0,
    "done": true
  },
  {
    "file_date": "2020-04-24",
    "end_date": "2020-03-31",
    "shares": 57.26686,
    "value": 71532035.0,
    "done": true
  },
  {
    "file_date": "2020-04-27",
    "end_date": "2020-03-31",
    "shares": 57.267501,
    "value": 71532835.0,
    "done": true
  },
  {
    "file_date": "2020-04-29",
    "end_date": "2020-03-31",
    "shares": 57.269189,
    "value": 71534944.0,
    "done": true
  },
  {
    "file_date": "2020-04-30",
    "end_date": "2020-03-31",
    "shares": 57.292735,
    "value": 71564355.0,
    "done": true
  },
  {
    "file_date": "2020-05-01",
    "end_date": "2020-03-31",
    "shares": 57.189719,
    "value": 71435678.0,
    "done": true
  },
  {
    "file_date": "2020-05-04",
    "end_date": "2020-03-31",
    "shares": 57.1869,
    "value": 71432157.0,
    "done": true
  },
  {
    "file_date": "2020-05-05",
    "end_date": "2020-03-31",
    "shares": 57.1869,
    "value": 71432157.0,
    "done": true
  },
  {
    "file_date": "2020-05-06",
    "end_date": "2020-03-31",
    "shares": 57.152417,
    "value": 71389084.0,
    "done": true
  },
  {
    "file_date": "2020-05-07",
    "end_date": "2020-03-31",
    "shares": 56.961688,
    "value": 71390084.0,
    "done": true
  },
  {
    "file_date": "2020-05-08",
    "end_date": "2020-03-31",
    "shares": 56.983829,
    "value": 71417833.0,
    "done": true
  },
  {
    "file_date": "2020-05-11",
    "end_date": "2020-03-31",
    "shares": 57.014668,
    "value": 71456484.0,
    "done": true
  },
  {
    "file_date": "2020-05-12",
    "end_date": "2020-03-31",
    "shares": 57.252189,
    "value": 71754169.0,
    "done": true
  },
  {
    "file_date": "2020-05-13",
    "end_date": "2020-03-31",
    "shares": 57.239478,
    "value": 71738238.0,
    "done": true
  },
  {
    "file_date": "2020-05-14",
    "end_date": "2020-03-31",
    "shares": 56.798853,
    "value": 71186002.0,
    "done": true
  },
  {
    "file_date": "2020-05-15",
    "end_date": "2020-03-31",
    "shares": 59.840354,
    "value": 74997916.0,
    "done": true
  },
  {
    "file_date": "2020-05-18",
    "end_date": "2020-03-31",
    "shares": 59.841692,
    "value": 74999593.0,
    "done": true
  },
  {
    "file_date": "2020-05-20",
    "end_date": "2020-03-31",
    "shares": 59.841692,
    "value": 74999593.0,
    "done": true
  },
  {
    "file_date": "2020-05-21",
    "end_date": "2020-03-31",
    "shares": 59.868266,
    "value": 75032898.0,
    "done": true
  },
  {
    "file_date": "2020-05-26",
    "end_date": "2020-03-31",
    "shares": 59.868266,
    "value": 75032898.0,
    "done": true
  },
  {
    "file_date": "2020-06-16",
    "end_date": "2020-03-31",
    "shares": 59.868266,
    "value": 75032898.0,
    "done": true
  },
  {
    "file_date": "2020-06-19",
    "end_date": "2020-03-31",
    "shares": 59.342043,
    "value": 74373382.0,
    "done": true
  },
  {
    "file_date": "2020-07-16",
    "end_date": "2020-06-30",
    "shares": 59.347438,
    "value": 74380144.0,
    "done": true
  },
  {
    "file_date": "2020-07-17",
    "end_date": "2020-06-30",
    "shares": 59.332803,
    "value": 74361802.0,
    "done": true
  },
  {
    "file_date": "2020-07-20",
    "end_date": "2020-06-30",
    "shares": 59.315606,
    "value": 74340249.0,
    "done": true
  },
  {
    "file_date": "2020-07-23",
    "end_date": "2020-06-30",
    "shares": 58.526671,
    "value": 73351477.0,
    "done": true
  },
  {
    "file_date": "2020-07-27",
    "end_date": "2020-06-30",
    "shares": 58.526041,
    "value": 73350687.0,
    "done": true
  },
  {
    "file_date": "2020-07-28",
    "end_date": "2020-06-30",
    "shares": 56.952856,
    "value": 71379015.0,
    "done": true
  },
  {
    "file_date": "2020-07-29",
    "end_date": "2020-06-30",
    "shares": 56.964492,
    "value": 71393598.0,
    "done": true
  },
  {
    "file_date": "2020-07-30",
    "end_date": "2020-06-30",
    "shares": 56.962852,
    "value": 71391542.0,
    "done": true
  },
  {
    "file_date": "2020-07-31",
    "end_date": "2020-06-30",
    "shares": 56.962713,
    "value": 71391368.0,
    "done": true
  },
  {
    "file_date": "2020-08-03",
    "end_date": "2020-06-30",
    "shares": 56.972873,
    "value": 71404102.0,
    "done": true
  },
  {
    "file_date": "2020-08-04",
    "end_date": "2020-06-30",
    "shares": 56.624671,
    "value": 70967700.0,
    "done": true
  },
  {
    "file_date": "2020-08-05",
    "end_date": "2020-06-30",
    "shares": 56.697809,
    "value": 71059364.0,
    "done": true
  },
  {
    "file_date": "2020-08-06",
    "end_date": "2020-06-30",
    "shares": 51.001671,
    "value": 71040227.0,
    "done": true
  },
  {
    "file_date": "2020-08-07",
    "end_date": "2020-06-30",
    "shares": 51.782651,
    "value": 72128054.0,
    "done": true
  },
  {
    "file_date": "2020-08-10",
    "end_date": "2020-06-30",
    "shares": 51.786873,
    "value": 72133936.0,
    "done": true
  },
  {
    "file_date": "2020-08-11",
    "end_date": "2020-06-30",
    "shares": 52.405633,
    "value": 72995806.0,
    "done": true
  },
  {
    "file_date": "2020-08-12",
    "end_date": "2020-06-30",
    "shares": 52.694018,
    "value": 73397497.0,
    "done": true
  },
  {
    "file_date": "2020-08-13",
    "end_date": "2020-06-30",
    "shares": 52.435046,
    "value": 73036776.0,
    "done": true
  },
  {
    "file_date": "2020-08-14",
    "end_date": "2020-06-30",
    "shares": 62.703535,
    "value": 87339754.0,
    "done": true
  },
  {
    "file_date": "2020-08-17",
    "end_date": "2020-06-30",
    "shares": 62.700888,
    "value": 87336067.0,
    "done": true
  },
  {
    "file_date": "2020-08-18",
    "end_date": "2020-06-30",
    "shares": 62.700888,
    "value": 87336067.0,
    "done": true
  },
  {
    "file_date": "2020-08-20",
    "end_date": "2020-06-30",
    "shares": 62.702324,
    "value": 87338067.0,
    "done": true
  },
  {
    "file_date": "2020-08-24",
    "end_date": "2020-06-30",
    "shares": 62.702324,
    "value": 87338067.0,
    "done": true
  },
  {
    "file_date": "2020-08-25",
    "end_date": "2020-06-30",
    "shares": 62.702324,
    "value": 87338067.0,
    "done": true
  },
  {
    "file_date": "2020-08-26",
    "end_date": "2020-06-30",
    "shares": 62.702482,
    "value": 87338287.0,
    "done": true
  },
  {
    "file_date": "2020-08-28",
    "end_date": "2020-06-30",
    "shares": 62.702482,
    "value": 87338287.0,
    "done": true
  },
  {
    "file_date": "2020-09-15",
    "end_date": "2020-06-30",
    "shares": 62.702482,
    "value": 87338287.0,
    "done": true
  },
  {
    "file_date": "2020-10-06",
    "end_date": "2020-09-30",
    "shares": 62.710673,
    "value": 87349697.0,
    "done": true
  },
  {
    "file_date": "2020-10-09",
    "end_date": "2020-09-30",
    "shares": 62.710889,
    "value": 87349997.0,
    "done": true
  },
  {
    "file_date": "2020-10-13",
    "end_date": "2020-09-30",
    "shares": 62.710889,
    "value": 87349997.0,
    "done": true
  },
  {
    "file_date": "2020-10-19",
    "end_date": "2020-09-30",
    "shares": 62.711712,
    "value": 87351143.0,
    "done": true
  },
  {
    "file_date": "2020-10-20",
    "end_date": "2020-09-30",
    "shares": 62.712681,
    "value": 87352493.0,
    "done": true
  },
  {
    "file_date": "2020-10-27",
    "end_date": "2020-09-30",
    "shares": 62.728559,
    "value": 87374610.0,
    "done": true
  },
  {
    "file_date": "2020-10-28",
    "end_date": "2020-09-30",
    "shares": 62.733944,
    "value": 87382110.0,
    "done": true
  },
  {
    "file_date": "2020-10-29",
    "end_date": "2020-09-30",
    "shares": 62.768332,
    "value": 87430010.0,
    "done": true
  },
  {
    "file_date": "2020-10-30",
    "end_date": "2020-09-30",
    "shares": 62.788177,
    "value": 87457652.0,
    "done": true
  },
  {
    "file_date": "2020-11-02",
    "end_date": "2020-09-30",
    "shares": 62.801791,
    "value": 87476615.0,
    "done": true
  },
  {
    "file_date": "2020-11-03",
    "end_date": "2020-09-30",
    "shares": 62.835508,
    "value": 87523579.0,
    "done": true
  },
  {
    "file_date": "2020-11-04",
    "end_date": "2020-09-30",
    "shares": 62.839185,
    "value": 87528701.0,
    "done": true
  },
  {
    "file_date": "2020-11-05",
    "end_date": "2020-09-30",
    "shares": 62.414055,
    "value": 87554437.0,
    "done": true
  },
  {
    "file_date": "2020-11-06",
    "end_date": "2020-09-30",
    "shares": 62.784438,
    "value": 88074009.0,
    "done": true
  },
  {
    "file_date": "2020-11-09",
    "end_date": "2020-09-30",
    "shares": 62.778122,
    "value": 88065150.0,
    "done": true
  },
  {
    "file_date": "2020-11-10",
    "end_date": "2020-09-30",
    "shares": 62.998914,
    "value": 88374877.0,
    "done": true
  },
  {
    "file_date": "2020-11-12",
    "end_date": "2020-09-30",
    "shares": 64.930398,
    "value": 91084362.0,
    "done": true
  },
  {
    "file_date": "2020-11-13",
    "end_date": "2020-09-30",
    "shares": 64.491379,
    "value": 90468506.0,
    "done": true
  },
  {
    "file_date": "2020-11-16",
    "end_date": "2020-09-30",
    "shares": 64.295625,
    "value": 90193903.0,
    "done": true
  },
  {
    "file_date": "2020-11-17",
    "end_date": "2020-09-30",
    "shares": 64.308005,
    "value": 90211270.0,
    "done": true
  },
  {
    "file_date": "2020-11-18",
    "end_date": "2020-09-30",
    "shares": 64.308005,
    "value": 90211270.0,
    "done": true
  },
  {
    "file_date": "2020-12-09",
    "end_date": "2020-09-30",
    "shares": 64.308005,
    "value": 90211270.0,
    "done": true
  },
  {
    "file_date": "2020-12-14",
    "end_date": "2020-09-30",
    "shares": 64.263606,
    "value": 90148987.0,
    "done": true
  },
  {
    "file_date": "2021-01-12",
    "end_date": "2020-12-31",
    "shares": 64.294466,
    "value": 90192277.0,
    "done": true
  },
  {
    "file_date": "2021-01-13",
    "end_date": "2020-12-31",
    "shares": 64.297094,
    "value": 90195963.0,
    "done": true
  },
  {
    "file_date": "2021-01-19",
    "end_date": "2020-12-31",
    "shares": 64.297379,
    "value": 90196363.0,
    "done": true
  },
  {
    "file_date": "2021-01-20",
    "end_date": "2020-12-31",
    "shares": 64.304734,
    "value": 90206681.0,
    "done": true
  },
  {
    "file_date": "2021-01-21",
    "end_date": "2020-12-31",
    "shares": 64.034462,
    "value": 89827543.0,
    "done": true
  },
  {
    "file_date": "2021-01-25",
    "end_date": "2020-12-31",
    "shares": 64.033856,
    "value": 89826693.0,
    "done": true
  },
  {
    "file_date": "2021-01-28",
    "end_date": "2020-12-31",
    "shares": 64.036592,
    "value": 89830531.0,
    "done": true
  },
  {
    "file_date": "2021-01-29",
    "end_date": "2020-12-31",
    "shares": 64.044576,
    "value": 89841731.0,
    "done": true
  },
  {
    "file_date": "2021-02-01",
    "end_date": "2020-12-31",
    "shares": 63.905133,
    "value": 89646120.0,
    "done": true
  },
  {
    "file_date": "2021-02-02",
    "end_date": "2020-12-31",
    "shares": 63.908936,
    "value": 89651455.0,
    "done": true
  },
  {
    "file_date": "2021-02-03",
    "end_date": "2020-12-31",
    "shares": 63.914555,
    "value": 89659338.0,
    "done": true
  },
  {
    "file_date": "2021-02-04",
    "end_date": "2020-12-31",
    "shares": 63.971062,
    "value": 89738606.0,
    "done": true
  },
  {
    "file_date": "2021-02-05",
    "end_date": "2020-12-31",
    "shares": 64.095069,
    "value": 89912563.0,
    "done": true
  },
  {
    "file_date": "2021-02-08",
    "end_date": "2020-12-31",
    "shares": 61.480105,
    "value": 86244291.0,
    "done": true
  },
  {
    "file_date": "2021-02-09",
    "end_date": "2020-12-31",
    "shares": 61.564619,
    "value": 86362847.0,
    "done": true
  },
  {
    "file_date": "2021-02-10",
    "end_date": "2020-12-31",
    "shares": 61.763837,
    "value": 86642311.0,
    "done": true
  },
  {
    "file_date": "2021-02-11",
    "end_date": "2020-12-31",
    "shares": 61.939704,
    "value": 86889017.0,
    "done": true
  },
  {
    "file_date": "2021-02-12",
    "end_date": "2020-12-31",
    "shares": 62.138033,
    "value": 87167232.0,
    "done": true
  },
  {
    "file_date": "2021-02-16",
    "end_date": "2020-12-31",
    "shares": 63.831056,
    "value": 89542205.0,
    "done": true
  },
  {
    "file_date": "2021-02-17",
    "end_date": "2020-12-31",
    "shares": 63.830971,
    "value": 89542086.0,
    "done": true
  },
  {
    "file_date": "2021-02-19",
    "end_date": "2020-12-31",
    "shares": 63.830971,
    "value": 89542086.0,
    "done": true
  },
  {
    "file_date": "2021-02-23",
    "end_date": "2020-12-31",
    "shares": 63.830971,
    "value": 89542086.0,
    "done": true
  },
  {
    "file_date": "2021-02-25",
    "end_date": "2020-12-31",
    "shares": 63.830971,
    "value": 89542086.0,
    "done": true
  },
  {
    "file_date": "2021-03-01",
    "end_date": "2020-12-31",
    "shares": 63.665871,
    "value": 89546047.0,
    "done": true
  },
  {
    "file_date": "2021-03-02",
    "end_date": "2020-12-31",
    "shares": 64.473697,
    "value": 90682255.0,
    "done": true
  },
  {
    "file_date": "2021-03-03",
    "end_date": "2020-12-31",
    "shares": 64.473697,
    "value": 90682255.0,
    "done": true
  },
  {
    "file_date": "2021-03-04",
    "end_date": "2020-12-31",
    "shares": 64.473697,
    "value": 90682255.0,
    "done": true
  },
  {
    "file_date": "2021-03-08",
    "end_date": "2020-12-31",
    "shares": 64.473697,
    "value": 90682255.0,
    "done": true
  },
  {
    "file_date": "2021-03-09",
    "end_date": "2020-12-31",
    "shares": 64.473697,
    "value": 90682255.0,
    "done": true
  },
  {
    "file_date": "2021-03-10",
    "end_date": "2020-12-31",
    "shares": 64.473697,
    "value": 90682255.0,
    "done": true
  },
  {
    "file_date": "2021-03-12",
    "end_date": "2020-12-31",
    "shares": 64.477039,
    "value": 90686955.0,
    "done": true
  },
  {
    "file_date": "2021-03-26",
    "end_date": "2020-12-31",
    "shares": 64.477039,
    "value": 90686955.0,
    "done": true
  },
  {
    "file_date": "2021-04-05",
    "end_date": "2021-03-31",
    "shares": 64.475047,
    "value": 90684153.0,
    "done": true
  },
  {
    "file_date": "2021-04-09",
    "end_date": "2021-03-31",
    "shares": 64.475047,
    "value": 90684153.0,
    "done": true
  },
  {
    "file_date": "2021-04-14",
    "end_date": "2021-03-31",
    "shares": 64.475047,
    "value": 90684153.0,
    "done": true
  },
  {
    "file_date": "2021-04-20",
    "end_date": "2021-03-31",
    "shares": 64.315502,
    "value": 90459753.0,
    "done": true
  },
  {
    "file_date": "2021-04-22",
    "end_date": "2021-03-31",
    "shares": 64.315502,
    "value": 90459753.0,
    "done": true
  },
  {
    "file_date": "2021-04-23",
    "end_date": "2021-03-31",
    "shares": 64.697185,
    "value": 90996591.0,
    "done": true
  },
  {
    "file_date": "2021-04-26",
    "end_date": "2021-03-31",
    "shares": 64.711589,
    "value": 91016850.0,
    "done": true
  },
  {
    "file_date": "2021-04-27",
    "end_date": "2021-03-31",
    "shares": 64.720961,
    "value": 91030032.0,
    "done": true
  },
  {
    "file_date": "2021-04-28",
    "end_date": "2021-03-31",
    "shares": 64.730966,
    "value": 91044103.0,
    "done": true
  },
  {
    "file_date": "2021-04-29",
    "end_date": "2021-03-31",
    "shares": 64.731018,
    "value": 91044177.0,
    "done": true
  },
  {
    "file_date": "2021-04-30",
    "end_date": "2021-03-31",
    "shares": 64.731007,
    "value": 91044162.0,
    "done": true
  },
  {
    "file_date": "2021-05-03",
    "end_date": "2021-03-31",
    "shares": 64.731716,
    "value": 91045159.0,
    "done": true
  },
  {
    "file_date": "2021-05-04",
    "end_date": "2021-03-31",
    "shares": 64.709669,
    "value": 91014149.0,
    "done": true
  },
  {
    "file_date": "2021-05-05",
    "end_date": "2021-03-31",
    "shares": 64.694806,
    "value": 90993244.0,
    "done": true
  },
  {
    "file_date": "2021-05-06",
    "end_date": "2021-03-31",
    "shares": 64.266346,
    "value": 90962586.0,
    "done": true
  },
  {
    "file_date": "2021-05-07",
    "end_date": "2021-03-31",
    "shares": 64.1239,
    "value": 90760968.0,
    "done": true
  },
  {
    "file_date": "2021-05-10",
    "end_date": "2021-03-31",
    "shares": 64.222423,
    "value": 90900417.0,
    "done": true
  },
  {
    "file_date": "2021-05-11",
    "end_date": "2021-03-31",
    "shares": 64.210377,
    "value": 90883367.0,
    "done": true
  },
  {
    "file_date": "2021-05-12",
    "end_date": "2021-03-31",
    "shares": 64.692656,
    "value": 91565986.0,
    "done": true
  },
  {
    "file_date": "2021-05-13",
    "end_date": "2021-03-31",
    "shares": 64.872224,
    "value": 91820146.0,
    "done": true
  },
  {
    "file_date": "2021-05-14",
    "end_date": "2021-03-31",
    "shares": 64.292282,
    "value": 90999296.0,
    "done": true
  },
  {
    "file_date": "2021-05-17",
    "end_date": "2021-03-31",
    "shares": 63.615434,
    "value": 90041285.0,
    "done": true
  },
  {
    "file_date": "2021-05-18",
    "end_date": "2021-03-31",
    "shares": 63.605533,
    "value": 90027271.0,
    "done": true
  },
  {
    "file_date": "2021-05-21",
    "end_date": "2021-03-31",
    "shares": 63.605533,
    "value": 90027271.0,
    "done": true
  },
  {
    "file_date": "2021-06-10",
    "end_date": "2021-03-31",
    "shares": 63.605533,
    "value": 90027271.0,
    "done": true
  },
  {
    "file_date": "2021-07-06",
    "end_date": "2021-06-30",
    "shares": 63.605533,
    "value": 90027271.0,
    "done": true
  },
  {
    "file_date": "2021-07-08",
    "end_date": "2021-06-30",
    "shares": 63.608959,
    "value": 90032121.0,
    "done": true
  },
  {
    "file_date": "2021-07-09",
    "end_date": "2021-03-31",
    "shares": 61.24063,
    "value": 86679988.0,
    "done": true
  },
  {
    "file_date": "2021-07-13",
    "end_date": "2021-06-30",
    "shares": 61.238328,
    "value": 86676730.0,
    "done": true
  },
  {
    "file_date": "2021-07-15",
    "end_date": "2021-06-30",
    "shares": 61.238328,
    "value": 86676730.0,
    "done": true
  },
  {
    "file_date": "2021-07-16",
    "end_date": "2021-06-30",
    "shares": 61.341072,
    "value": 86822153.0,
    "done": true
  },
  {
    "file_date": "2021-07-19",
    "end_date": "2021-06-30",
    "shares": 61.365791,
    "value": 86857141.0,
    "done": true
  },
  {
    "file_date": "2021-07-20",
    "end_date": "2021-03-31",
    "shares": 61.363036,
    "value": 86853241.0,
    "done": true
  },
  {
    "file_date": "2021-07-21",
    "end_date": "2021-03-31",
    "shares": 61.377102,
    "value": 86873150.0,
    "done": true
  },
  {
    "file_date": "2021-07-23",
    "end_date": "2021-06-30",
    "shares": 61.384918,
    "value": 86884213.0,
    "done": true
  },
  {
    "file_date": "2021-07-26",
    "end_date": "2021-06-30",
    "shares": 61.401029,
    "value": 86907016.0,
    "done": true
  },
  {
    "file_date": "2021-07-29",
    "end_date": "2021-06-30",
    "shares": 61.401029,
    "value": 86907016.0,
    "done": true
  },
  {
    "file_date": "2021-07-30",
    "end_date": "2021-06-30",
    "shares": 61.852152,
    "value": 87545536.0,
    "done": true
  },
  {
    "file_date": "2021-08-02",
    "end_date": "2021-06-30",
    "shares": 61.862473,
    "value": 87560144.0,
    "done": true
  },
  {
    "file_date": "2021-08-03",
    "end_date": "2021-06-30",
    "shares": 61.228214,
    "value": 86662414.0,
    "done": true
  },
  {
    "file_date": "2021-08-04",
    "end_date": "2021-06-30",
    "shares": 61.206414,
    "value": 86631558.0,
    "done": true
  },
  {
    "file_date": "2021-08-05",
    "end_date": "2021-06-30",
    "shares": 60.958058,
    "value": 86670167.0,
    "done": true
  },
  {
    "file_date": "2021-08-06",
    "end_date": "2021-06-30",
    "shares": 61.004752,
    "value": 86736556.0,
    "done": true
  },
  {
    "file_date": "2021-08-09",
    "end_date": "2021-06-30",
    "shares": 61.044071,
    "value": 86792460.0,
    "done": true
  },
  {
    "file_date": "2021-08-10",
    "end_date": "2021-06-30",
    "shares": 62.712946,
    "value": 89165267.0,
    "done": true
  },
  {
    "file_date": "2021-08-11",
    "end_date": "2021-06-30",
    "shares": 63.775011,
    "value": 90675310.0,
    "done": true
  },
  {
    "file_date": "2021-08-12",
    "end_date": "2021-06-30",
    "shares": 63.953053,
    "value": 90928451.0,
    "done": true
  },
  {
    "file_date": "2021-08-13",
    "end_date": "2021-06-30",
    "shares": 65.689786,
    "value": 93397738.0,
    "done": true
  },
  {
    "file_date": "2021-08-16",
    "end_date": "2021-06-30",
    "shares": 61.4026,
    "value": 87302216.0,
    "done": true
  },
  {
    "file_date": "2021-08-17",
    "end_date": "2021-06-30",
    "shares": 61.415426,
    "value": 87320452.0,
    "done": true
  },
  {
    "file_date": "2021-08-19",
    "end_date": "2021-06-30",
    "shares": 61.444512,
    "value": 87361807.0,
    "done": true
  },
  {
    "file_date": "2021-08-23",
    "end_date": "2021-06-30",
    "shares": 61.444512,
    "value": 87361807.0,
    "done": true
  },
  {
    "file_date": "2021-09-03",
    "end_date": "2021-06-30",
    "shares": 61.444512,
    "value": 87361807.0,
    "done": true
  },
  {
    "file_date": "2021-09-13",
    "end_date": "2021-06-30",
    "shares": 61.444512,
    "value": 87361807.0,
    "done": true
  }
]