[
  {
    "file_date": "2013-07-29",
    "end_date": "2013-06-30",
    "shares": 0.094063,
    "value": 24193,
    "done": true
  },
  {
    "file_date": "2013-07-31",
    "end_date": "2013-06-30",
    "shares": 0.133153,
    "value": 34247,
    "done": true
  },
  {
    "file_date": "2013-08-02",
    "end_date": "2013-06-30",
    "shares": 0.51418,
    "value": 132247,
    "done": true
  },
  {
    "file_date": "2013-08-05",
    "end_date": "2013-06-30",
    "shares": 1.486372,
    "value": 382295,
    "done": true
  },
  {
    "file_date": "2013-08-07",
    "end_date": "2013-06-30",
    "shares": 1.496839,
    "value": 384987,
    "done": true
  },
  {
    "file_date": "2013-08-09",
    "end_date": "2013-06-30",
    "shares": 2.117554,
    "value": 544635,
    "done": true
  },
  {
    "file_date": "2013-08-12",
    "end_date": "2013-06-30",
    "shares": 2.315292,
    "value": 595493,
    "done": true
  },
  {
    "file_date": "2013-08-13",
    "end_date": "2013-06-30",
    "shares": 7.681248,
    "value": 1975617,
    "done": true
  },
  {
    "file_date": "2013-08-14",
    "end_date": "2013-06-30",
    "shares": 24.584047,
    "value": 6323017,
    "done": true
  },
  {
    "file_date": "2013-10-24",
    "end_date": "2013-09-30",
    "shares": 24.526831,
    "value": 6323017,
    "done": true
  },
  {
    "file_date": "2013-10-28",
    "end_date": "2013-09-30",
    "shares": 25.418995,
    "value": 6553017,
    "done": true
  },
  {
    "file_date": "2013-10-29",
    "end_date": "2013-09-30",
    "shares": 25.41917,
    "value": 6553062,
    "done": true
  },
  {
    "file_date": "2013-10-31",
    "end_date": "2013-09-30",
    "shares": 25.439236,
    "value": 6558235,
    "done": true
  },
  {
    "file_date": "2013-11-05",
    "end_date": "2013-09-30",
    "shares": 25.474065,
    "value": 6567214,
    "done": true
  },
  {
    "file_date": "2013-11-06",
    "end_date": "2013-09-30",
    "shares": 25.489612,
    "value": 6571222,
    "done": true
  },
  {
    "file_date": "2013-11-08",
    "end_date": "2013-09-30",
    "shares": 25.541978,
    "value": 6584722,
    "done": true
  },
  {
    "file_date": "2013-11-12",
    "end_date": "2013-09-30",
    "shares": 26.157514,
    "value": 6743407,
    "done": true
  },
  {
    "file_date": "2013-11-13",
    "end_date": "2013-09-30",
    "shares": 26.919057,
    "value": 6939733,
    "done": true
  },
  {
    "file_date": "2013-11-14",
    "end_date": "2013-09-30",
    "shares": 25.886924,
    "value": 6673649.0,
    "done": true
  },
  {
    "file_date": "2014-01-14",
    "end_date": "2013-12-31",
    "shares": 25.382525,
    "value": 6706063.0,
    "done": true
  },
  {
    "file_date": "2014-01-30",
    "end_date": "2013-12-31",
    "shares": 25.381011,
    "value": 6705663.0,
    "done": true
  },
  {
    "file_date": "2014-01-31",
    "end_date": "2013-12-31",
    "shares": 25.426139,
    "value": 6717586.0,
    "done": true
  },
  {
    "file_date": "2014-02-03",
    "end_date": "2013-12-31",
    "shares": 25.79707,
    "value": 6815586.0,
    "done": true
  },
  {
    "file_date": "2014-02-04",
    "end_date": "2013-12-31",
    "shares": 25.843301,
    "value": 6827800.0,
    "done": true
  },
  {
    "file_date": "2014-02-05",
    "end_date": "2013-12-31",
    "shares": 25.993115,
    "value": 6867381.0,
    "done": true
  },
  {
    "file_date": "2014-02-06",
    "end_date": "2013-12-31",
    "shares": 26.061484,
    "value": 6885444.0,
    "done": true
  },
  {
    "file_date": "2014-02-07",
    "end_date": "2013-12-31",
    "shares": 26.060878,
    "value": 6885284.0,
    "done": true
  },
  {
    "file_date": "2014-02-10",
    "end_date": "2013-12-31",
    "shares": 27.781457,
    "value": 7339861.0,
    "done": true
  },
  {
    "file_date": "2014-02-11",
    "end_date": "2013-12-31",
    "shares": 27.909447,
    "value": 7373676.0,
    "done": true
  },
  {
    "file_date": "2014-02-12",
    "end_date": "2013-12-31",
    "shares": 30.595409,
    "value": 8083307.0,
    "done": true
  },
  {
    "file_date": "2014-02-13",
    "end_date": "2013-12-31",
    "shares": 36.235405,
    "value": 9573394.0,
    "done": true
  },
  {
    "file_date": "2014-02-14",
    "end_date": "2013-12-31",
    "shares": 50.216472,
    "value": 13267192.0,
    "done": true
  },
  {
    "file_date": "2014-04-03",
    "end_date": "2014-03-31",
    "shares": 49.816394,
    "value": 13330867.0,
    "done": true
  },
  {
    "file_date": "2014-04-07",
    "end_date": "2014-03-31",
    "shares": 49.85157,
    "value": 13340280.0,
    "done": true
  },
  {
    "file_date": "2014-04-11",
    "end_date": "2014-03-31",
    "shares": 49.851943,
    "value": 13340380.0,
    "done": true
  },
  {
    "file_date": "2014-04-18",
    "end_date": "2014-03-31",
    "shares": 49.80432,
    "value": 13327636.0,
    "done": true
  },
  {
    "file_date": "2014-04-22",
    "end_date": "2014-03-31",
    "shares": 50.050583,
    "value": 13393536.0,
    "done": true
  },
  {
    "file_date": "2014-04-24",
    "end_date": "2014-03-31",
    "shares": 50.166842,
    "value": 13424647.0,
    "done": true
  },
  {
    "file_date": "2014-04-25",
    "end_date": "2014-03-31",
    "shares": 50.195404,
    "value": 13432290.0,
    "done": true
  },
  {
    "file_date": "2014-04-28",
    "end_date": "2014-03-31",
    "shares": 50.181951,
    "value": 13428690.0,
    "done": true
  },
  {
    "file_date": "2014-04-29",
    "end_date": "2014-03-31",
    "shares": 50.184865,
    "value": 13429470.0,
    "done": true
  },
  {
    "file_date": "2014-05-01",
    "end_date": "2014-03-31",
    "shares": 50.185007,
    "value": 13429508.0,
    "done": true
  },
  {
    "file_date": "2014-05-02",
    "end_date": "2014-03-31",
    "shares": 51.059058,
    "value": 13663404.0,
    "done": true
  },
  {
    "file_date": "2014-05-05",
    "end_date": "2014-03-31",
    "shares": 51.082309,
    "value": 13669626.0,
    "done": true
  },
  {
    "file_date": "2014-05-06",
    "end_date": "2014-03-31",
    "shares": 51.281237,
    "value": 13722859.0,
    "done": true
  },
  {
    "file_date": "2014-05-07",
    "end_date": "2014-03-31",
    "shares": 51.400845,
    "value": 13754866.0,
    "done": true
  },
  {
    "file_date": "2014-05-09",
    "end_date": "2014-03-31",
    "shares": 51.475676,
    "value": 13774891.0,
    "done": true
  },
  {
    "file_date": "2014-05-12",
    "end_date": "2014-03-31",
    "shares": 51.077794,
    "value": 13775681.0,
    "done": true
  },
  {
    "file_date": "2014-05-13",
    "end_date": "2014-03-31",
    "shares": 53.696667,
    "value": 14481991.0,
    "done": true
  },
  {
    "file_date": "2014-05-14",
    "end_date": "2014-03-31",
    "shares": 54.820211,
    "value": 14785011.0,
    "done": true
  },
  {
    "file_date": "2014-05-15",
    "end_date": "2014-03-31",
    "shares": 54.328925,
    "value": 14652511.0,
    "done": true
  },
  {
    "file_date": "2014-07-08",
    "end_date": "2014-06-30",
    "shares": 54.392421,
    "value": 14669636.0,
    "done": true
  },
  {
    "file_date": "2014-07-21",
    "end_date": "2014-06-30",
    "shares": 54.684201,
    "value": 14748329.0,
    "done": true
  },
  {
    "file_date": "2014-07-30",
    "end_date": "2014-06-30",
    "shares": 54.925087,
    "value": 14813296.0,
    "done": true
  },
  {
    "file_date": "2014-07-31",
    "end_date": "2014-06-30",
    "shares": 55.154205,
    "value": 14875089.0,
    "done": true
  },
  {
    "file_date": "2014-08-01",
    "end_date": "2014-06-30",
    "shares": 55.578569,
    "value": 14989540.0,
    "done": true
  },
  {
    "file_date": "2014-08-04",
    "end_date": "2014-06-30",
    "shares": 56.317512,
    "value": 15188833.0,
    "done": true
  },
  {
    "file_date": "2014-08-05",
    "end_date": "2014-06-30",
    "shares": 56.318565,
    "value": 15189117.0,
    "done": true
  },
  {
    "file_date": "2014-08-06",
    "end_date": "2014-06-30",
    "shares": 58.686211,
    "value": 15827671.0,
    "done": true
  },
  {
    "file_date": "2014-08-07",
    "end_date": "2014-06-30",
    "shares": 58.809455,
    "value": 15860910.0,
    "done": true
  },
  {
    "file_date": "2014-08-08",
    "end_date": "2014-06-30",
    "shares": 45.226541,
    "value": 16132307.0,
    "done": true
  },
  {
    "file_date": "2014-08-11",
    "end_date": "2014-06-30",
    "shares": 46.218663,
    "value": 16486197.0,
    "done": true
  },
  {
    "file_date": "2014-08-12",
    "end_date": "2014-06-30",
    "shares": 47.052789,
    "value": 16783730.0,
    "done": true
  },
  {
    "file_date": "2014-08-13",
    "end_date": "2014-06-30",
    "shares": 48.148778,
    "value": 17174669.0,
    "done": true
  },
  {
    "file_date": "2014-08-14",
    "end_date": "2014-06-30",
    "shares": 62.917098,
    "value": 22442529.0,
    "done": true
  },
  {
    "file_date": "2014-10-06",
    "end_date": "2014-09-30",
    "shares": 63.013188,
    "value": 22476804.0,
    "done": true
  },
  {
    "file_date": "2014-10-10",
    "end_date": "2014-09-30",
    "shares": 63.013468,
    "value": 22476904.0,
    "done": true
  },
  {
    "file_date": "2014-10-14",
    "end_date": "2014-09-30",
    "shares": 63.900437,
    "value": 22793286.0,
    "done": true
  },
  {
    "file_date": "2014-10-16",
    "end_date": "2014-09-30",
    "shares": 64.165646,
    "value": 22887886.0,
    "done": true
  },
  {
    "file_date": "2014-10-28",
    "end_date": "2014-09-30",
    "shares": 70.074968,
    "value": 24995741.0,
    "done": true
  },
  {
    "file_date": "2014-10-29",
    "end_date": "2014-09-30",
    "shares": 69.951458,
    "value": 24951685.0,
    "done": true
  },
  {
    "file_date": "2014-10-30",
    "end_date": "2014-09-30",
    "shares": 69.951458,
    "value": 24951685.0,
    "done": true
  },
  {
    "file_date": "2014-10-31",
    "end_date": "2014-09-30",
    "shares": 69.954211,
    "value": 24952667.0,
    "done": true
  },
  {
    "file_date": "2014-11-04",
    "end_date": "2014-09-30",
    "shares": 69.953479,
    "value": 24952406.0,
    "done": true
  },
  {
    "file_date": "2014-11-05",
    "end_date": "2014-09-30",
    "shares": 70.233101,
    "value": 25052147.0,
    "done": true
  },
  {
    "file_date": "2014-11-06",
    "end_date": "2014-09-30",
    "shares": 70.21358,
    "value": 25045184.0,
    "done": true
  },
  {
    "file_date": "2014-11-07",
    "end_date": "2014-09-30",
    "shares": 70.755812,
    "value": 25238598.0,
    "done": true
  },
  {
    "file_date": "2014-11-10",
    "end_date": "2014-09-30",
    "shares": 70.827138,
    "value": 25837740.0,
    "done": true
  },
  {
    "file_date": "2014-11-12",
    "end_date": "2014-09-30",
    "shares": 71.305822,
    "value": 26012364.0,
    "done": true
  },
  {
    "file_date": "2014-11-13",
    "end_date": "2014-09-30",
    "shares": 72.654334,
    "value": 26504301.0,
    "done": true
  },
  {
    "file_date": "2014-11-14",
    "end_date": "2014-09-30",
    "shares": 76.677706,
    "value": 27972027.0,
    "done": true
  },
  {
    "file_date": "2015-01-05",
    "end_date": "2014-12-31",
    "shares": 76.897634,
    "value": 28052257.0,
    "done": true
  },
  {
    "file_date": "2015-01-15",
    "end_date": "2014-12-31",
    "shares": 76.910071,
    "value": 28056794.0,
    "done": true
  },
  {
    "file_date": "2015-01-21",
    "end_date": "2014-12-31",
    "shares": 80.783084,
    "value": 29469669.0,
    "done": true
  },
  {
    "file_date": "2015-01-23",
    "end_date": "2014-12-31",
    "shares": 80.783906,
    "value": 29469969.0,
    "done": true
  },
  {
    "file_date": "2015-01-26",
    "end_date": "2014-12-31",
    "shares": 80.784454,
    "value": 29470169.0,
    "done": true
  },
  {
    "file_date": "2015-01-27",
    "end_date": "2014-12-31",
    "shares": 80.788533,
    "value": 29471657.0,
    "done": true
  },
  {
    "file_date": "2015-01-28",
    "end_date": "2014-12-31",
    "shares": 80.790452,
    "value": 29472357.0,
    "done": true
  },
  {
    "file_date": "2015-01-29",
    "end_date": "2014-12-31",
    "shares": 80.790452,
    "value": 29472357.0,
    "done": true
  },
  {
    "file_date": "2015-01-30",
    "end_date": "2014-12-31",
    "shares": 80.815751,
    "value": 29481586.0,
    "done": true
  },
  {
    "file_date": "2015-02-02",
    "end_date": "2014-12-31",
    "shares": 83.694772,
    "value": 30531853.0,
    "done": true
  },
  {
    "file_date": "2015-02-03",
    "end_date": "2014-12-31",
    "shares": 83.784764,
    "value": 30564682.0,
    "done": true
  },
  {
    "file_date": "2015-02-04",
    "end_date": "2014-12-31",
    "shares": 83.790773,
    "value": 30566874.0,
    "done": true
  },
  {
    "file_date": "2015-02-06",
    "end_date": "2014-12-31",
    "shares": 83.735085,
    "value": 30546559.0,
    "done": true
  },
  {
    "file_date": "2015-02-09",
    "end_date": "2014-12-31",
    "shares": 85.335905,
    "value": 31130538.0,
    "done": true
  },
  {
    "file_date": "2015-02-10",
    "end_date": "2014-12-31",
    "shares": 85.453448,
    "value": 31173418.0,
    "done": true
  },
  {
    "file_date": "2015-02-11",
    "end_date": "2014-12-31",
    "shares": 85.804049,
    "value": 31301317.0,
    "done": true
  },
  {
    "file_date": "2015-02-12",
    "end_date": "2014-12-31",
    "shares": 86.561735,
    "value": 31577721.0,
    "done": true
  },
  {
    "file_date": "2015-02-13",
    "end_date": "2014-12-31",
    "shares": 52.851944,
    "value": 19280389.0,
    "done": true
  },
  {
    "file_date": "2015-04-08",
    "end_date": "2015-03-31",
    "shares": 47.051241,
    "value": 19333355.0,
    "done": true
  },
  {
    "file_date": "2015-04-10",
    "end_date": "2015-03-31",
    "shares": 47.051285,
    "value": 19333373.0,
    "done": true
  },
  {
    "file_date": "2015-04-13",
    "end_date": "2015-03-31",
    "shares": 47.05872,
    "value": 19336428.0,
    "done": true
  },
  {
    "file_date": "2015-04-15",
    "end_date": "2015-03-31",
    "shares": 46.99082,
    "value": 19308528.0,
    "done": true
  },
  {
    "file_date": "2015-04-21",
    "end_date": "2015-03-31",
    "shares": 46.992954,
    "value": 19309405.0,
    "done": true
  },
  {
    "file_date": "2015-04-22",
    "end_date": "2015-03-31",
    "shares": 47.085782,
    "value": 19347548.0,
    "done": true
  },
  {
    "file_date": "2015-04-23",
    "end_date": "2015-03-31",
    "shares": 47.178262,
    "value": 19385548.0,
    "done": true
  },
  {
    "file_date": "2015-04-24",
    "end_date": "2015-03-31",
    "shares": 47.20844,
    "value": 19397948.0,
    "done": true
  },
  {
    "file_date": "2015-04-27",
    "end_date": "2015-03-31",
    "shares": 47.366629,
    "value": 19462948.0,
    "done": true
  },
  {
    "file_date": "2015-04-28",
    "end_date": "2015-03-31",
    "shares": 47.406055,
    "value": 19479148.0,
    "done": true
  },
  {
    "file_date": "2015-04-30",
    "end_date": "2015-03-31",
    "shares": 47.517481,
    "value": 19524933.0,
    "done": true
  },
  {
    "file_date": "2015-05-01",
    "end_date": "2015-03-31",
    "shares": 47.517481,
    "value": 19524933.0,
    "done": true
  },
  {
    "file_date": "2015-05-04",
    "end_date": "2015-03-31",
    "shares": 48.15855,
    "value": 19788348.0,
    "done": true
  },
  {
    "file_date": "2015-05-05",
    "end_date": "2015-03-31",
    "shares": 48.284293,
    "value": 19840016.0,
    "done": true
  },
  {
    "file_date": "2015-05-06",
    "end_date": "2015-03-31",
    "shares": 48.333424,
    "value": 19860204.0,
    "done": true
  },
  {
    "file_date": "2015-05-07",
    "end_date": "2015-03-31",
    "shares": 48.553049,
    "value": 19950448.0,
    "done": true
  },
  {
    "file_date": "2015-05-08",
    "end_date": "2015-03-31",
    "shares": 48.672675,
    "value": 19999602.0,
    "done": true
  },
  {
    "file_date": "2015-05-11",
    "end_date": "2015-03-31",
    "shares": 47.519654,
    "value": 19525826.0,
    "done": true
  },
  {
    "file_date": "2015-05-12",
    "end_date": "2015-03-31",
    "shares": 48.843422,
    "value": 20182102.0,
    "done": true
  },
  {
    "file_date": "2015-05-13",
    "end_date": "2015-03-31",
    "shares": 50.632188,
    "value": 20921220.0,
    "done": true
  },
  {
    "file_date": "2015-05-14",
    "end_date": "2015-03-31",
    "shares": 67.790363,
    "value": 28010978.0,
    "done": true
  },
  {
    "file_date": "2015-05-15",
    "end_date": "2015-03-31",
    "shares": 84.283139,
    "value": 34825793.0,
    "done": true
  },
  {
    "file_date": "2015-07-02",
    "end_date": "2015-06-30",
    "shares": 84.283139,
    "value": 34825793.0,
    "done": true
  },
  {
    "file_date": "2015-07-15",
    "end_date": "2015-06-30",
    "shares": 84.270978,
    "value": 34820768.0,
    "done": true
  },
  {
    "file_date": "2015-07-17",
    "end_date": "2015-06-30",
    "shares": 84.271704,
    "value": 34821068.0,
    "done": true
  },
  {
    "file_date": "2015-07-21",
    "end_date": "2015-06-30",
    "shares": 84.341888,
    "value": 34850068.0,
    "done": true
  },
  {
    "file_date": "2015-07-22",
    "end_date": "2015-06-30",
    "shares": 84.342507,
    "value": 34850324.0,
    "done": true
  },
  {
    "file_date": "2015-07-23",
    "end_date": "2015-06-30",
    "shares": 84.338379,
    "value": 34848618.0,
    "done": true
  },
  {
    "file_date": "2015-07-24",
    "end_date": "2015-06-30",
    "shares": 84.338379,
    "value": 34848618.0,
    "done": true
  },
  {
    "file_date": "2015-07-27",
    "end_date": "2015-06-30",
    "shares": 84.357256,
    "value": 34856418.0,
    "done": true
  },
  {
    "file_date": "2015-07-28",
    "end_date": "2015-06-30",
    "shares": 85.160249,
    "value": 35188215.0,
    "done": true
  },
  {
    "file_date": "2015-07-29",
    "end_date": "2015-06-30",
    "shares": 85.209835,
    "value": 35208704.0,
    "done": true
  },
  {
    "file_date": "2015-07-30",
    "end_date": "2015-06-30",
    "shares": 85.264785,
    "value": 35231409.0,
    "done": true
  },
  {
    "file_date": "2015-07-31",
    "end_date": "2015-06-30",
    "shares": 85.241493,
    "value": 35221785.0,
    "done": true
  },
  {
    "file_date": "2015-08-03",
    "end_date": "2015-06-30",
    "shares": 85.85037,
    "value": 35473373.0,
    "done": true
  },
  {
    "file_date": "2015-08-04",
    "end_date": "2015-06-30",
    "shares": 85.950731,
    "value": 35514842.0,
    "done": true
  },
  {
    "file_date": "2015-08-05",
    "end_date": "2015-06-30",
    "shares": 86.05031,
    "value": 35555988.0,
    "done": true
  },
  {
    "file_date": "2015-08-06",
    "end_date": "2015-06-30",
    "shares": 86.034976,
    "value": 35549652.0,
    "done": true
  },
  {
    "file_date": "2015-08-07",
    "end_date": "2015-06-30",
    "shares": 77.982635,
    "value": 35926600.0,
    "done": true
  },
  {
    "file_date": "2015-08-10",
    "end_date": "2015-06-30",
    "shares": 78.121374,
    "value": 35990517.0,
    "done": true
  },
  {
    "file_date": "2015-08-11",
    "end_date": "2015-06-30",
    "shares": 78.226156,
    "value": 36038790.0,
    "done": true
  },
  {
    "file_date": "2015-08-12",
    "end_date": "2015-06-30",
    "shares": 78.748335,
    "value": 36279358.0,
    "done": true
  },
  {
    "file_date": "2015-08-13",
    "end_date": "2015-06-30",
    "shares": 84.397623,
    "value": 38881985.0,
    "done": true
  },
  {
    "file_date": "2015-08-14",
    "end_date": "2015-06-30",
    "shares": 82.257033,
    "value": 37895815.0,
    "done": true
  },
  {
    "file_date": "2015-10-01",
    "end_date": "2015-09-30",
    "shares": 82.257033,
    "value": 37895815.0,
    "done": true
  },
  {
    "file_date": "2015-10-09",
    "end_date": "2015-09-30",
    "shares": 82.272906,
    "value": 37903128.0,
    "done": true
  },
  {
    "file_date": "2015-10-13",
    "end_date": "2015-09-30",
    "shares": 82.273341,
    "value": 37903328.0,
    "done": true
  },
  {
    "file_date": "2015-10-19",
    "end_date": "2015-09-30",
    "shares": 82.309234,
    "value": 37919864.0,
    "done": true
  },
  {
    "file_date": "2015-10-20",
    "end_date": "2015-09-30",
    "shares": 81.787992,
    "value": 37679728.0,
    "done": true
  },
  {
    "file_date": "2015-10-21",
    "end_date": "2015-09-30",
    "shares": 81.794888,
    "value": 37682905.0,
    "done": true
  },
  {
    "file_date": "2015-10-23",
    "end_date": "2015-09-30",
    "shares": 81.880927,
    "value": 37722543.0,
    "done": true
  },
  {
    "file_date": "2015-10-26",
    "end_date": "2015-09-30",
    "shares": 81.864988,
    "value": 37715200.0,
    "done": true
  },
  {
    "file_date": "2015-10-28",
    "end_date": "2015-09-30",
    "shares": 81.952518,
    "value": 37755525.0,
    "done": true
  },
  {
    "file_date": "2015-10-29",
    "end_date": "2015-09-30",
    "shares": 81.458811,
    "value": 37528074.0,
    "done": true
  },
  {
    "file_date": "2015-10-30",
    "end_date": "2015-09-30",
    "shares": 81.497565,
    "value": 37545928.0,
    "done": true
  },
  {
    "file_date": "2015-11-02",
    "end_date": "2015-09-30",
    "shares": 81.528689,
    "value": 37560267.0,
    "done": true
  },
  {
    "file_date": "2015-11-03",
    "end_date": "2015-09-30",
    "shares": 81.582993,
    "value": 37585285.0,
    "done": true
  },
  {
    "file_date": "2015-11-04",
    "end_date": "2015-09-30",
    "shares": 81.88371,
    "value": 37723825.0,
    "done": true
  },
  {
    "file_date": "2015-11-05",
    "end_date": "2015-09-30",
    "shares": 81.88371,
    "value": 37723825.0,
    "done": true
  },
  {
    "file_date": "2015-11-06",
    "end_date": "2015-09-30",
    "shares": 81.675365,
    "value": 37693181.0,
    "done": true
  },
  {
    "file_date": "2015-11-09",
    "end_date": "2015-09-30",
    "shares": 81.913647,
    "value": 37803148.0,
    "done": true
  },
  {
    "file_date": "2015-11-10",
    "end_date": "2015-09-30",
    "shares": 82.746076,
    "value": 38187314.0,
    "done": true
  },
  {
    "file_date": "2015-11-12",
    "end_date": "2015-09-30",
    "shares": 83.612737,
    "value": 38587278.0,
    "done": true
  },
  {
    "file_date": "2015-11-13",
    "end_date": "2015-09-30",
    "shares": 69.097575,
    "value": 31888531.0,
    "done": true
  },
  {
    "file_date": "2016-01-11",
    "end_date": "2015-12-31",
    "shares": 69.089125,
    "value": 31884631.0,
    "done": true
  },
  {
    "file_date": "2016-01-13",
    "end_date": "2015-12-31",
    "shares": 69.253595,
    "value": 31960534.0,
    "done": true
  },
  {
    "file_date": "2016-01-15",
    "end_date": "2015-12-31",
    "shares": 69.253595,
    "value": 31960534.0,
    "done": true
  },
  {
    "file_date": "2016-01-19",
    "end_date": "2015-12-31",
    "shares": 69.686964,
    "value": 32160534.0,
    "done": true
  },
  {
    "file_date": "2016-01-20",
    "end_date": "2015-12-31",
    "shares": 69.721012,
    "value": 32176247.0,
    "done": true
  },
  {
    "file_date": "2016-01-22",
    "end_date": "2015-12-31",
    "shares": 69.722212,
    "value": 32176801.0,
    "done": true
  },
  {
    "file_date": "2016-01-25",
    "end_date": "2015-12-31",
    "shares": 69.722862,
    "value": 32177101.0,
    "done": true
  },
  {
    "file_date": "2016-01-27",
    "end_date": "2015-12-31",
    "shares": 69.73654,
    "value": 32183413.0,
    "done": true
  },
  {
    "file_date": "2016-01-28",
    "end_date": "2015-12-31",
    "shares": 69.74172,
    "value": 32185804.0,
    "done": true
  },
  {
    "file_date": "2016-01-29",
    "end_date": "2015-12-31",
    "shares": 69.771343,
    "value": 32199475.0,
    "done": true
  },
  {
    "file_date": "2016-02-01",
    "end_date": "2015-12-31",
    "shares": 70.274052,
    "value": 32431475.0,
    "done": true
  },
  {
    "file_date": "2016-02-02",
    "end_date": "2015-12-31",
    "shares": 70.274052,
    "value": 32431475.0,
    "done": true
  },
  {
    "file_date": "2016-02-03",
    "end_date": "2015-12-31",
    "shares": 70.249931,
    "value": 32420343.0,
    "done": true
  },
  {
    "file_date": "2016-02-04",
    "end_date": "2015-12-31",
    "shares": 70.468592,
    "value": 32521255.0,
    "done": true
  },
  {
    "file_date": "2016-02-05",
    "end_date": "2015-12-31",
    "shares": 70.811053,
    "value": 32679301.0,
    "done": true
  },
  {
    "file_date": "2016-02-08",
    "end_date": "2015-12-31",
    "shares": 70.802284,
    "value": 32675254.0,
    "done": true
  },
  {
    "file_date": "2016-02-09",
    "end_date": "2015-12-31",
    "shares": 72.720074,
    "value": 33560314.0,
    "done": true
  },
  {
    "file_date": "2016-02-10",
    "end_date": "2015-12-31",
    "shares": 73.583298,
    "value": 33958692.0,
    "done": true
  },
  {
    "file_date": "2016-02-11",
    "end_date": "2015-12-31",
    "shares": 73.329619,
    "value": 33841619.0,
    "done": true
  },
  {
    "file_date": "2016-02-12",
    "end_date": "2015-12-31",
    "shares": 54.944256,
    "value": 25356774.0,
    "done": true
  },
  {
    "file_date": "2016-04-08",
    "end_date": "2016-03-31",
    "shares": 54.901849,
    "value": 25353674.0,
    "done": true
  },
  {
    "file_date": "2016-04-13",
    "end_date": "2016-03-31",
    "shares": 54.901849,
    "value": 25353674.0,
    "done": true
  },
  {
    "file_date": "2016-04-14",
    "end_date": "2016-03-31",
    "shares": 54.95079,
    "value": 25376275.0,
    "done": true
  },
  {
    "file_date": "2016-04-18",
    "end_date": "2016-03-31",
    "shares": 54.95079,
    "value": 25376275.0,
    "done": true
  },
  {
    "file_date": "2016-04-19",
    "end_date": "2016-03-31",
    "shares": 55.479158,
    "value": 25620275.0,
    "done": true
  },
  {
    "file_date": "2016-04-21",
    "end_date": "2016-03-31",
    "shares": 55.479158,
    "value": 25620275.0,
    "done": true
  },
  {
    "file_date": "2016-04-22",
    "end_date": "2016-03-31",
    "shares": 55.479158,
    "value": 25620275.0,
    "done": true
  },
  {
    "file_date": "2016-04-26",
    "end_date": "2016-03-31",
    "shares": 55.479385,
    "value": 25620380.0,
    "done": true
  },
  {
    "file_date": "2016-04-28",
    "end_date": "2016-03-31",
    "shares": 55.523644,
    "value": 25640819.0,
    "done": true
  },
  {
    "file_date": "2016-04-29",
    "end_date": "2016-03-31",
    "shares": 55.603038,
    "value": 25677483.0,
    "done": true
  },
  {
    "file_date": "2016-05-02",
    "end_date": "2016-03-31",
    "shares": 56.015422,
    "value": 25867922.0,
    "done": true
  },
  {
    "file_date": "2016-05-03",
    "end_date": "2016-03-31",
    "shares": 56.037707,
    "value": 25878213.0,
    "done": true
  },
  {
    "file_date": "2016-05-04",
    "end_date": "2016-03-31",
    "shares": 56.054597,
    "value": 25886013.0,
    "done": true
  },
  {
    "file_date": "2016-05-05",
    "end_date": "2016-03-31",
    "shares": 55.938712,
    "value": 25832497.0,
    "done": true
  },
  {
    "file_date": "2016-05-06",
    "end_date": "2016-03-31",
    "shares": 58.406929,
    "value": 26972320.0,
    "done": true
  },
  {
    "file_date": "2016-05-09",
    "end_date": "2016-03-31",
    "shares": 59.103393,
    "value": 27293947.0,
    "done": true
  },
  {
    "file_date": "2016-05-10",
    "end_date": "2016-03-31",
    "shares": 58.161407,
    "value": 26876386.0,
    "done": true
  },
  {
    "file_date": "2016-05-11",
    "end_date": "2016-03-31",
    "shares": 58.087739,
    "value": 26842344.0,
    "done": true
  },
  {
    "file_date": "2016-05-12",
    "end_date": "2016-03-31",
    "shares": 60.059747,
    "value": 27753609.0,
    "done": true
  },
  {
    "file_date": "2016-05-13",
    "end_date": "2016-03-31",
    "shares": 38.954951,
    "value": 18001083.0,
    "done": true
  },
  {
    "file_date": "2016-07-06",
    "end_date": "2016-06-30",
    "shares": 38.958561,
    "value": 18002751.0,
    "done": true
  },
  {
    "file_date": "2016-07-12",
    "end_date": "2016-06-30",
    "shares": 38.994975,
    "value": 18019578.0,
    "done": true
  },
  {
    "file_date": "2016-07-19",
    "end_date": "2016-06-30",
    "shares": 39.082082,
    "value": 18059830.0,
    "done": true
  },
  {
    "file_date": "2016-07-20",
    "end_date": "2016-06-30",
    "shares": 39.082082,
    "value": 18059830.0,
    "done": true
  },
  {
    "file_date": "2016-07-21",
    "end_date": "2016-06-30",
    "shares": 39.082082,
    "value": 18059830.0,
    "done": true
  },
  {
    "file_date": "2016-07-22",
    "end_date": "2016-06-30",
    "shares": 39.11879,
    "value": 18076793.0,
    "done": true
  },
  {
    "file_date": "2016-07-25",
    "end_date": "2016-06-30",
    "shares": 39.170699,
    "value": 18100780.0,
    "done": true
  },
  {
    "file_date": "2016-07-27",
    "end_date": "2016-06-30",
    "shares": 39.198881,
    "value": 18113803.0,
    "done": true
  },
  {
    "file_date": "2016-07-28",
    "end_date": "2016-06-30",
    "shares": 39.198881,
    "value": 18113803.0,
    "done": true
  },
  {
    "file_date": "2016-08-01",
    "end_date": "2016-06-30",
    "shares": 39.79578,
    "value": 18389630.0,
    "done": true
  },
  {
    "file_date": "2016-08-02",
    "end_date": "2016-06-30",
    "shares": 39.460355,
    "value": 18234630.0,
    "done": true
  },
  {
    "file_date": "2016-08-03",
    "end_date": "2016-06-30",
    "shares": 39.450907,
    "value": 18230264.0,
    "done": true
  },
  {
    "file_date": "2016-08-04",
    "end_date": "2016-06-30",
    "shares": 39.643356,
    "value": 18319195.0,
    "done": true
  },
  {
    "file_date": "2016-08-05",
    "end_date": "2016-06-30",
    "shares": 39.643339,
    "value": 18319187.0,
    "done": true
  },
  {
    "file_date": "2016-08-08",
    "end_date": "2016-06-30",
    "shares": 39.81694,
    "value": 18399408.0,
    "done": true
  },
  {
    "file_date": "2016-08-09",
    "end_date": "2016-06-30",
    "shares": 34.854622,
    "value": 16106321.0,
    "done": true
  },
  {
    "file_date": "2016-08-10",
    "end_date": "2016-06-30",
    "shares": 33.667628,
    "value": 15557811.0,
    "done": true
  },
  {
    "file_date": "2016-08-11",
    "end_date": "2016-06-30",
    "shares": 49.497245,
    "value": 22872677.0,
    "done": true
  },
  {
    "file_date": "2016-08-12",
    "end_date": "2016-06-30",
    "shares": 44.841054,
    "value": 20721051.0,
    "done": true
  },
  {
    "file_date": "2016-10-05",
    "end_date": "2016-09-30",
    "shares": 44.844293,
    "value": 20722548.0,
    "done": true
  },
  {
    "file_date": "2016-10-07",
    "end_date": "2016-09-30",
    "shares": 44.84559,
    "value": 20723147.0,
    "done": true
  },
  {
    "file_date": "2016-10-11",
    "end_date": "2016-09-30",
    "shares": 44.848836,
    "value": 20724647.0,
    "done": true
  },
  {
    "file_date": "2016-10-12",
    "end_date": "2016-09-30",
    "shares": 44.866358,
    "value": 20732744.0,
    "done": true
  },
  {
    "file_date": "2016-10-19",
    "end_date": "2016-09-30",
    "shares": 44.868842,
    "value": 20733892.0,
    "done": true
  },
  {
    "file_date": "2016-10-20",
    "end_date": "2016-09-30",
    "shares": 45.141757,
    "value": 20860006.0,
    "done": true
  },
  {
    "file_date": "2016-10-24",
    "end_date": "2016-09-30",
    "shares": 45.128989,
    "value": 20854106.0,
    "done": true
  },
  {
    "file_date": "2016-10-25",
    "end_date": "2016-09-30",
    "shares": 45.128989,
    "value": 20854106.0,
    "done": true
  },
  {
    "file_date": "2016-10-27",
    "end_date": "2016-09-30",
    "shares": 45.128989,
    "value": 20854106.0,
    "done": true
  },
  {
    "file_date": "2016-10-28",
    "end_date": "2016-09-30",
    "shares": 45.409208,
    "value": 20983595.0,
    "done": true
  },
  {
    "file_date": "2016-10-31",
    "end_date": "2016-09-30",
    "shares": 45.405222,
    "value": 20981753.0,
    "done": true
  },
  {
    "file_date": "2016-11-01",
    "end_date": "2016-09-30",
    "shares": 45.392627,
    "value": 20975933.0,
    "done": true
  },
  {
    "file_date": "2016-11-02",
    "end_date": "2016-09-30",
    "shares": 45.379632,
    "value": 20969928.0,
    "done": true
  },
  {
    "file_date": "2016-11-03",
    "end_date": "2016-09-30",
    "shares": 45.361796,
    "value": 20961686.0,
    "done": true
  },
  {
    "file_date": "2016-11-04",
    "end_date": "2016-09-30",
    "shares": 46.87026,
    "value": 21658747.0,
    "done": true
  },
  {
    "file_date": "2016-11-07",
    "end_date": "2016-09-30",
    "shares": 46.87026,
    "value": 21658747.0,
    "done": true
  },
  {
    "file_date": "2016-11-08",
    "end_date": "2016-09-30",
    "shares": 46.978115,
    "value": 21760263.0,
    "done": true
  },
  {
    "file_date": "2016-11-09",
    "end_date": "2016-09-30",
    "shares": 47.165725,
    "value": 21847164.0,
    "done": true
  },
  {
    "file_date": "2016-11-10",
    "end_date": "2016-09-30",
    "shares": 47.872308,
    "value": 22174453.0,
    "done": true
  },
  {
    "file_date": "2016-11-14",
    "end_date": "2016-09-30",
    "shares": 63.512856,
    "value": 29419155.0,
    "done": true
  },
  {
    "file_date": "2017-01-09",
    "end_date": "2016-12-31",
    "shares": 63.512856,
    "value": 29419155.0,
    "done": true
  },
  {
    "file_date": "2017-01-11",
    "end_date": "2016-12-31",
    "shares": 63.528148,
    "value": 29426238.0,
    "done": true
  },
  {
    "file_date": "2017-01-12",
    "end_date": "2016-12-31",
    "shares": 63.515417,
    "value": 29420341.0,
    "done": true
  },
  {
    "file_date": "2017-01-13",
    "end_date": "2016-12-31",
    "shares": 63.517576,
    "value": 29421341.0,
    "done": true
  },
  {
    "file_date": "2017-01-19",
    "end_date": "2016-12-31",
    "shares": 63.870099,
    "value": 29584630.0,
    "done": true
  },
  {
    "file_date": "2017-01-24",
    "end_date": "2016-12-31",
    "shares": 63.838998,
    "value": 29570224.0,
    "done": true
  },
  {
    "file_date": "2017-01-25",
    "end_date": "2016-12-31",
    "shares": 63.870086,
    "value": 29584624.0,
    "done": true
  },
  {
    "file_date": "2017-01-26",
    "end_date": "2016-12-31",
    "shares": 64.421323,
    "value": 29839957.0,
    "done": true
  },
  {
    "file_date": "2017-01-27",
    "end_date": "2016-12-31",
    "shares": 64.988633,
    "value": 30102735.0,
    "done": true
  },
  {
    "file_date": "2017-01-31",
    "end_date": "2016-12-31",
    "shares": 64.98777,
    "value": 30102335.0,
    "done": true
  },
  {
    "file_date": "2017-02-01",
    "end_date": "2016-12-31",
    "shares": 65.262856,
    "value": 30229755.0,
    "done": true
  },
  {
    "file_date": "2017-02-02",
    "end_date": "2016-12-31",
    "shares": 65.2641,
    "value": 30230331.0,
    "done": true
  },
  {
    "file_date": "2017-02-03",
    "end_date": "2016-12-31",
    "shares": 65.269065,
    "value": 30232631.0,
    "done": true
  },
  {
    "file_date": "2017-02-06",
    "end_date": "2016-12-31",
    "shares": 65.250989,
    "value": 30224258.0,
    "done": true
  },
  {
    "file_date": "2017-02-07",
    "end_date": "2016-12-31",
    "shares": 65.080285,
    "value": 30145188.0,
    "done": true
  },
  {
    "file_date": "2017-02-08",
    "end_date": "2016-12-31",
    "shares": 65.080285,
    "value": 30145188.0,
    "done": true
  },
  {
    "file_date": "2017-02-09",
    "end_date": "2016-12-31",
    "shares": 65.812239,
    "value": 30484229.0,
    "done": true
  },
  {
    "file_date": "2017-02-10",
    "end_date": "2016-12-31",
    "shares": 65.164562,
    "value": 30184225.0,
    "done": true
  },
  {
    "file_date": "2017-02-13",
    "end_date": "2016-12-31",
    "shares": 64.265212,
    "value": 29767646.0,
    "done": true
  },
  {
    "file_date": "2017-02-14",
    "end_date": "2016-12-31",
    "shares": 65.051859,
    "value": 30132021.0,
    "done": true
  },
  {
    "file_date": "2017-04-07",
    "end_date": "2017-03-31",
    "shares": 64.71654,
    "value": 30132021.0,
    "done": true
  },
  {
    "file_date": "2017-04-11",
    "end_date": "2017-03-31",
    "shares": 64.727206,
    "value": 30136987.0,
    "done": true
  },
  {
    "file_date": "2017-04-21",
    "end_date": "2017-03-31",
    "shares": 64.731452,
    "value": 30138964.0,
    "done": true
  },
  {
    "file_date": "2017-04-25",
    "end_date": "2017-03-31",
    "shares": 64.398956,
    "value": 29984154.0,
    "done": true
  },
  {
    "file_date": "2017-04-26",
    "end_date": "2017-03-31",
    "shares": 64.398956,
    "value": 29984154.0,
    "done": true
  },
  {
    "file_date": "2017-04-27",
    "end_date": "2017-03-31",
    "shares": 64.489699,
    "value": 30026404.0,
    "done": true
  },
  {
    "file_date": "2017-04-28",
    "end_date": "2017-03-31",
    "shares": 64.325833,
    "value": 29950108.0,
    "done": true
  },
  {
    "file_date": "2017-05-01",
    "end_date": "2017-03-31",
    "shares": 64.419981,
    "value": 29993943.0,
    "done": true
  },
  {
    "file_date": "2017-05-02",
    "end_date": "2017-03-31",
    "shares": 64.422878,
    "value": 29995292.0,
    "done": true
  },
  {
    "file_date": "2017-05-03",
    "end_date": "2017-03-31",
    "shares": 64.456229,
    "value": 30010820.0,
    "done": true
  },
  {
    "file_date": "2017-05-04",
    "end_date": "2017-03-31",
    "shares": 64.501531,
    "value": 30031913.0,
    "done": true
  },
  {
    "file_date": "2017-05-05",
    "end_date": "2017-03-31",
    "shares": 64.730142,
    "value": 30138354.0,
    "done": true
  },
  {
    "file_date": "2017-05-08",
    "end_date": "2017-03-31",
    "shares": 64.790286,
    "value": 30166357.0,
    "done": true
  },
  {
    "file_date": "2017-05-09",
    "end_date": "2017-03-31",
    "shares": 64.874085,
    "value": 30205374.0,
    "done": true
  },
  {
    "file_date": "2017-05-10",
    "end_date": "2017-03-31",
    "shares": 64.802105,
    "value": 30230182.0,
    "done": true
  },
  {
    "file_date": "2017-05-11",
    "end_date": "2017-03-31",
    "shares": 64.842774,
    "value": 30249154.0,
    "done": true
  },
  {
    "file_date": "2017-05-12",
    "end_date": "2017-03-31",
    "shares": 73.494699,
    "value": 34285277.0,
    "done": true
  },
  {
    "file_date": "2017-05-15",
    "end_date": "2017-03-31",
    "shares": 67.636028,
    "value": 31552207.0,
    "done": true
  },
  {
    "file_date": "2017-07-11",
    "end_date": "2017-06-30",
    "shares": 67.552583,
    "value": 31513280.0,
    "done": true
  },
  {
    "file_date": "2017-07-13",
    "end_date": "2017-06-30",
    "shares": 67.551689,
    "value": 31512863.0,
    "done": true
  },
  {
    "file_date": "2017-07-19",
    "end_date": "2017-06-30",
    "shares": 67.255325,
    "value": 31374609.0,
    "done": true
  },
  {
    "file_date": "2017-07-20",
    "end_date": "2017-06-30",
    "shares": 67.254253,
    "value": 31374109.0,
    "done": true
  },
  {
    "file_date": "2017-07-21",
    "end_date": "2017-06-30",
    "shares": 67.284178,
    "value": 31388069.0,
    "done": true
  },
  {
    "file_date": "2017-07-24",
    "end_date": "2017-06-30",
    "shares": 67.284178,
    "value": 31388069.0,
    "done": true
  },
  {
    "file_date": "2017-07-25",
    "end_date": "2017-06-30",
    "shares": 66.662279,
    "value": 31097953.0,
    "done": true
  },
  {
    "file_date": "2017-07-26",
    "end_date": "2017-06-30",
    "shares": 66.662279,
    "value": 31097953.0,
    "done": true
  },
  {
    "file_date": "2017-07-27",
    "end_date": "2017-06-30",
    "shares": 66.662279,
    "value": 31097953.0,
    "done": true
  },
  {
    "file_date": "2017-07-28",
    "end_date": "2017-06-30",
    "shares": 66.667638,
    "value": 31100453.0,
    "done": true
  },
  {
    "file_date": "2017-07-31",
    "end_date": "2017-06-30",
    "shares": 66.667638,
    "value": 31100453.0,
    "done": true
  },
  {
    "file_date": "2017-08-02",
    "end_date": "2017-06-30",
    "shares": 66.582285,
    "value": 31060636.0,
    "done": true
  },
  {
    "file_date": "2017-08-03",
    "end_date": "2017-06-30",
    "shares": 66.687492,
    "value": 31109715.0,
    "done": true
  },
  {
    "file_date": "2017-08-04",
    "end_date": "2017-06-30",
    "shares": 66.707981,
    "value": 31119273.0,
    "done": true
  },
  {
    "file_date": "2017-08-07",
    "end_date": "2017-06-30",
    "shares": 66.533061,
    "value": 31037673.0,
    "done": true
  },
  {
    "file_date": "2017-08-08",
    "end_date": "2017-06-30",
    "shares": 66.005437,
    "value": 31055558.0,
    "done": true
  },
  {
    "file_date": "2017-08-09",
    "end_date": "2017-06-30",
    "shares": 64.984085,
    "value": 30575012.0,
    "done": true
  },
  {
    "file_date": "2017-08-10",
    "end_date": "2017-06-30",
    "shares": 65.614914,
    "value": 30871817.0,
    "done": true
  },
  {
    "file_date": "2017-08-11",
    "end_date": "2017-06-30",
    "shares": 67.627241,
    "value": 31818617.0,
    "done": true
  },
  {
    "file_date": "2017-08-14",
    "end_date": "2017-06-30",
    "shares": 59.217373,
    "value": 27861774.0,
    "done": true
  },
  {
    "file_date": "2017-10-16",
    "end_date": "2017-09-30",
    "shares": 59.214295,
    "value": 27860326.0,
    "done": true
  },
  {
    "file_date": "2017-10-17",
    "end_date": "2017-09-30",
    "shares": 59.214295,
    "value": 27860326.0,
    "done": true
  },
  {
    "file_date": "2017-10-18",
    "end_date": "2017-09-30",
    "shares": 59.220939,
    "value": 27863452.0,
    "done": true
  },
  {
    "file_date": "2017-10-20",
    "end_date": "2017-09-30",
    "shares": 59.220939,
    "value": 27863452.0,
    "done": true
  },
  {
    "file_date": "2017-10-23",
    "end_date": "2017-09-30",
    "shares": 59.274062,
    "value": 27888446.0,
    "done": true
  },
  {
    "file_date": "2017-10-24",
    "end_date": "2017-09-30",
    "shares": 59.272867,
    "value": 27887884.0,
    "done": true
  },
  {
    "file_date": "2017-10-25",
    "end_date": "2017-09-30",
    "shares": 59.272867,
    "value": 27887884.0,
    "done": true
  },
  {
    "file_date": "2017-10-27",
    "end_date": "2017-09-30",
    "shares": 59.263388,
    "value": 27883424.0,
    "done": true
  },
  {
    "file_date": "2017-10-30",
    "end_date": "2017-09-30",
    "shares": 59.262325,
    "value": 27882924.0,
    "done": true
  },
  {
    "file_date": "2017-10-31",
    "end_date": "2017-09-30",
    "shares": 59.262325,
    "value": 27882924.0,
    "done": true
  },
  {
    "file_date": "2017-11-01",
    "end_date": "2017-09-30",
    "shares": 59.262325,
    "value": 27882924.0,
    "done": true
  },
  {
    "file_date": "2017-11-03",
    "end_date": "2017-09-30",
    "shares": 59.270661,
    "value": 27886846.0,
    "done": true
  },
  {
    "file_date": "2017-11-06",
    "end_date": "2017-09-30",
    "shares": 59.269224,
    "value": 27886170.0,
    "done": true
  },
  {
    "file_date": "2017-11-07",
    "end_date": "2017-09-30",
    "shares": 59.507947,
    "value": 27998489.0,
    "done": true
  },
  {
    "file_date": "2017-11-08",
    "end_date": "2017-09-30",
    "shares": 59.569996,
    "value": 28027683.0,
    "done": true
  },
  {
    "file_date": "2017-11-09",
    "end_date": "2017-09-30",
    "shares": 59.705097,
    "value": 28139012.0,
    "done": true
  },
  {
    "file_date": "2017-11-13",
    "end_date": "2017-09-30",
    "shares": 61.66738,
    "value": 29063836.0,
    "done": true
  },
  {
    "file_date": "2017-11-14",
    "end_date": "2017-09-30",
    "shares": 70.923533,
    "value": 33426261.0,
    "done": true
  },
  {
    "file_date": "2018-01-10",
    "end_date": "2017-12-31",
    "shares": 70.962181,
    "value": 33444476.0,
    "done": true
  },
  {
    "file_date": "2018-01-17",
    "end_date": "2017-12-31",
    "shares": 70.98502,
    "value": 33455240.0,
    "done": true
  },
  {
    "file_date": "2018-01-18",
    "end_date": "2017-12-31",
    "shares": 71.1132,
    "value": 33515651.0,
    "done": true
  },
  {
    "file_date": "2018-01-22",
    "end_date": "2017-12-31",
    "shares": 71.117231,
    "value": 33517551.0,
    "done": true
  },
  {
    "file_date": "2018-01-24",
    "end_date": "2017-12-31",
    "shares": 71.161209,
    "value": 33538278.0,
    "done": true
  },
  {
    "file_date": "2018-01-25",
    "end_date": "2017-12-31",
    "shares": 71.161209,
    "value": 33538278.0,
    "done": true
  },
  {
    "file_date": "2018-01-31",
    "end_date": "2017-12-31",
    "shares": 71.161209,
    "value": 33538278.0,
    "done": true
  },
  {
    "file_date": "2018-02-01",
    "end_date": "2017-12-31",
    "shares": 71.243976,
    "value": 33577286.0,
    "done": true
  },
  {
    "file_date": "2018-02-02",
    "end_date": "2017-12-31",
    "shares": 71.238844,
    "value": 33574867.0,
    "done": true
  },
  {
    "file_date": "2018-02-05",
    "end_date": "2017-12-31",
    "shares": 71.251152,
    "value": 33580668.0,
    "done": true
  },
  {
    "file_date": "2018-02-06",
    "end_date": "2017-12-31",
    "shares": 71.427261,
    "value": 33663668.0,
    "done": true
  },
  {
    "file_date": "2018-02-07",
    "end_date": "2017-12-31",
    "shares": 70.923168,
    "value": 33426089.0,
    "done": true
  },
  {
    "file_date": "2018-02-08",
    "end_date": "2017-12-31",
    "shares": 70.864059,
    "value": 33398231.0,
    "done": true
  },
  {
    "file_date": "2018-02-09",
    "end_date": "2017-12-31",
    "shares": 70.247564,
    "value": 33107677.0,
    "done": true
  },
  {
    "file_date": "2018-02-12",
    "end_date": "2017-12-31",
    "shares": 70.819648,
    "value": 33377300.0,
    "done": true
  },
  {
    "file_date": "2018-02-13",
    "end_date": "2017-12-31",
    "shares": 75.055665,
    "value": 35373735.0,
    "done": true
  },
  {
    "file_date": "2018-02-14",
    "end_date": "2017-12-31",
    "shares": 76.371447,
    "value": 35993863.0,
    "done": true
  },
  {
    "file_date": "2018-04-12",
    "end_date": "2018-03-31",
    "shares": 75.61056,
    "value": 36028432.0,
    "done": true
  },
  {
    "file_date": "2018-04-23",
    "end_date": "2018-03-31",
    "shares": 75.61056,
    "value": 36028432.0,
    "done": true
  },
  {
    "file_date": "2018-04-25",
    "end_date": "2018-03-31",
    "shares": 75.607412,
    "value": 36026932.0,
    "done": true
  },
  {
    "file_date": "2018-04-26",
    "end_date": "2018-03-31",
    "shares": 75.583664,
    "value": 36015616.0,
    "done": true
  },
  {
    "file_date": "2018-04-30",
    "end_date": "2018-03-31",
    "shares": 76.172556,
    "value": 36296223.0,
    "done": true
  },
  {
    "file_date": "2018-05-01",
    "end_date": "2018-03-31",
    "shares": 76.195572,
    "value": 36307190.0,
    "done": true
  },
  {
    "file_date": "2018-05-02",
    "end_date": "2018-03-31",
    "shares": 76.214204,
    "value": 36316068.0,
    "done": true
  },
  {
    "file_date": "2018-05-03",
    "end_date": "2018-03-31",
    "shares": 76.192594,
    "value": 36305771.0,
    "done": true
  },
  {
    "file_date": "2018-05-04",
    "end_date": "2018-03-31",
    "shares": 76.151299,
    "value": 36286094.0,
    "done": true
  },
  {
    "file_date": "2018-05-07",
    "end_date": "2018-03-31",
    "shares": 76.098875,
    "value": 36261114.0,
    "done": true
  },
  {
    "file_date": "2018-05-08",
    "end_date": "2018-03-31",
    "shares": 75.918668,
    "value": 36251164.0,
    "done": true
  },
  {
    "file_date": "2018-05-09",
    "end_date": "2018-03-31",
    "shares": 75.735537,
    "value": 36163719.0,
    "done": true
  },
  {
    "file_date": "2018-05-10",
    "end_date": "2018-03-31",
    "shares": 75.734593,
    "value": 36163268.0,
    "done": true
  },
  {
    "file_date": "2018-05-11",
    "end_date": "2018-03-31",
    "shares": 76.303252,
    "value": 36434803.0,
    "done": true
  },
  {
    "file_date": "2018-05-14",
    "end_date": "2018-03-31",
    "shares": 75.188693,
    "value": 35902601.0,
    "done": true
  },
  {
    "file_date": "2018-05-15",
    "end_date": "2018-03-31",
    "shares": 74.698182,
    "value": 35668382.0,
    "done": true
  },
  {
    "file_date": "2018-07-13",
    "end_date": "2018-06-30",
    "shares": 74.741889,
    "value": 35689252.0,
    "done": true
  },
  {
    "file_date": "2018-07-16",
    "end_date": "2018-06-30",
    "shares": 74.742542,
    "value": 35689564.0,
    "done": true
  },
  {
    "file_date": "2018-07-17",
    "end_date": "2018-06-30",
    "shares": 75.644932,
    "value": 36120455.0,
    "done": true
  },
  {
    "file_date": "2018-07-24",
    "end_date": "2018-06-30",
    "shares": 75.770769,
    "value": 36180542.0,
    "done": true
  },
  {
    "file_date": "2018-07-25",
    "end_date": "2018-06-30",
    "shares": 75.729426,
    "value": 36160801.0,
    "done": true
  },
  {
    "file_date": "2018-07-26",
    "end_date": "2018-06-30",
    "shares": 75.729426,
    "value": 36160801.0,
    "done": true
  },
  {
    "file_date": "2018-07-27",
    "end_date": "2018-06-30",
    "shares": 75.731028,
    "value": 36161566.0,
    "done": true
  },
  {
    "file_date": "2018-07-30",
    "end_date": "2018-06-30",
    "shares": 75.716787,
    "value": 36154766.0,
    "done": true
  },
  {
    "file_date": "2018-07-31",
    "end_date": "2018-06-30",
    "shares": 75.753185,
    "value": 36172146.0,
    "done": true
  },
  {
    "file_date": "2018-08-01",
    "end_date": "2018-06-30",
    "shares": 75.748913,
    "value": 36170106.0,
    "done": true
  },
  {
    "file_date": "2018-08-02",
    "end_date": "2018-06-30",
    "shares": 75.770042,
    "value": 36180195.0,
    "done": true
  },
  {
    "file_date": "2018-08-03",
    "end_date": "2018-06-30",
    "shares": 75.791489,
    "value": 36190436.0,
    "done": true
  },
  {
    "file_date": "2018-08-06",
    "end_date": "2018-06-30",
    "shares": 75.774599,
    "value": 36182371.0,
    "done": true
  },
  {
    "file_date": "2018-08-07",
    "end_date": "2018-06-30",
    "shares": 75.774777,
    "value": 36182456.0,
    "done": true
  },
  {
    "file_date": "2018-08-08",
    "end_date": "2018-06-30",
    "shares": 76.211983,
    "value": 36391222.0,
    "done": true
  },
  {
    "file_date": "2018-08-09",
    "end_date": "2018-06-30",
    "shares": 75.892128,
    "value": 36450989.0,
    "done": true
  },
  {
    "file_date": "2018-08-10",
    "end_date": "2018-06-30",
    "shares": 72.88686,
    "value": 35007559.0,
    "done": true
  },
  {
    "file_date": "2018-08-13",
    "end_date": "2018-06-30",
    "shares": 73.16199,
    "value": 35139704.0,
    "done": true
  },
  {
    "file_date": "2018-08-14",
    "end_date": "2018-06-30",
    "shares": 73.960775,
    "value": 35523360.0,
    "done": true
  },
  {
    "file_date": "2018-10-12",
    "end_date": "2018-09-30",
    "shares": 73.960972,
    "value": 35523455.0,
    "done": true
  },
  {
    "file_date": "2018-10-25",
    "end_date": "2018-09-30",
    "shares": 73.963054,
    "value": 35524455.0,
    "done": true
  },
  {
    "file_date": "2018-10-26",
    "end_date": "2018-09-30",
    "shares": 73.931824,
    "value": 35509455.0,
    "done": true
  },
  {
    "file_date": "2018-10-29",
    "end_date": "2018-09-30",
    "shares": 72.966583,
    "value": 35045850.0,
    "done": true
  },
  {
    "file_date": "2018-10-30",
    "end_date": "2018-09-30",
    "shares": 73.094047,
    "value": 35107071.0,
    "done": true
  },
  {
    "file_date": "2018-10-31",
    "end_date": "2018-09-30",
    "shares": 73.094047,
    "value": 35107071.0,
    "done": true
  },
  {
    "file_date": "2018-11-01",
    "end_date": "2018-09-30",
    "shares": 73.062526,
    "value": 35091931.0,
    "done": true
  },
  {
    "file_date": "2018-11-02",
    "end_date": "2018-09-30",
    "shares": 73.066265,
    "value": 35093727.0,
    "done": true
  },
  {
    "file_date": "2018-11-05",
    "end_date": "2018-09-30",
    "shares": 73.060643,
    "value": 35091027.0,
    "done": true
  },
  {
    "file_date": "2018-11-07",
    "end_date": "2018-09-30",
    "shares": 73.06339,
    "value": 35092346.0,
    "done": true
  },
  {
    "file_date": "2018-11-08",
    "end_date": "2018-09-30",
    "shares": 73.061516,
    "value": 35091446.0,
    "done": true
  },
  {
    "file_date": "2018-11-09",
    "end_date": "2018-09-30",
    "shares": 68.58251,
    "value": 34785049.0,
    "done": true
  },
  {
    "file_date": "2018-11-13",
    "end_date": "2018-09-30",
    "shares": 71.35167,
    "value": 36189567.0,
    "done": true
  },
  {
    "file_date": "2018-11-14",
    "end_date": "2018-09-30",
    "shares": 74.035002,
    "value": 37550553.0,
    "done": true
  },
  {
    "file_date": "2019-01-16",
    "end_date": "2018-12-31",
    "shares": 74.078458,
    "value": 37572594.0,
    "done": true
  },
  {
    "file_date": "2019-01-17",
    "end_date": "2018-12-31",
    "shares": 74.093074,
    "value": 37580007.0,
    "done": true
  },
  {
    "file_date": "2019-01-22",
    "end_date": "2018-12-31",
    "shares": 74.09585,
    "value": 37581415.0,
    "done": true
  },
  {
    "file_date": "2019-01-23",
    "end_date": "2018-12-31",
    "shares": 74.035554,
    "value": 37550833.0,
    "done": true
  },
  {
    "file_date": "2019-01-28",
    "end_date": "2018-12-31",
    "shares": 74.035554,
    "value": 37550833.0,
    "done": true
  },
  {
    "file_date": "2019-01-31",
    "end_date": "2018-12-31",
    "shares": 74.076276,
    "value": 37571487.0,
    "done": true
  },
  {
    "file_date": "2019-02-01",
    "end_date": "2018-12-31",
    "shares": 74.096037,
    "value": 37581510.0,
    "done": true
  },
  {
    "file_date": "2019-02-05",
    "end_date": "2018-12-31",
    "shares": 74.896491,
    "value": 37987500.0,
    "done": true
  },
  {
    "file_date": "2019-02-07",
    "end_date": "2018-12-31",
    "shares": 74.931719,
    "value": 38005368.0,
    "done": true
  },
  {
    "file_date": "2019-02-08",
    "end_date": "2018-12-31",
    "shares": 74.107399,
    "value": 37587273.0,
    "done": true
  },
  {
    "file_date": "2019-02-11",
    "end_date": "2018-12-31",
    "shares": 74.568093,
    "value": 37820937.0,
    "done": true
  },
  {
    "file_date": "2019-02-12",
    "end_date": "2018-12-31",
    "shares": 74.600254,
    "value": 37837249.0,
    "done": true
  },
  {
    "file_date": "2019-02-13",
    "end_date": "2018-12-31",
    "shares": 73.158602,
    "value": 37106043.0,
    "done": true
  },
  {
    "file_date": "2019-02-14",
    "end_date": "2018-12-31",
    "shares": 73.603375,
    "value": 37331632.0,
    "done": true
  },
  {
    "file_date": "2019-04-11",
    "end_date": "2019-03-31",
    "shares": 73.034153,
    "value": 37174384.0,
    "done": true
  },
  {
    "file_date": "2019-04-12",
    "end_date": "2019-03-31",
    "shares": 73.054631,
    "value": 37184807.0,
    "done": true
  },
  {
    "file_date": "2019-04-16",
    "end_date": "2019-03-31",
    "shares": 73.048513,
    "value": 37181693.0,
    "done": true
  },
  {
    "file_date": "2019-04-18",
    "end_date": "2019-03-31",
    "shares": 73.014639,
    "value": 37164451.0,
    "done": true
  },
  {
    "file_date": "2019-04-23",
    "end_date": "2019-03-31",
    "shares": 73.014639,
    "value": 37164451.0,
    "done": true
  },
  {
    "file_date": "2019-04-25",
    "end_date": "2019-03-31",
    "shares": 73.029039,
    "value": 37171781.0,
    "done": true
  },
  {
    "file_date": "2019-04-26",
    "end_date": "2019-03-31",
    "shares": 73.027248,
    "value": 37170869.0,
    "done": true
  },
  {
    "file_date": "2019-04-29",
    "end_date": "2019-03-31",
    "shares": 73.048008,
    "value": 37181436.0,
    "done": true
  },
  {
    "file_date": "2019-05-01",
    "end_date": "2019-03-31",
    "shares": 73.045228,
    "value": 37180021.0,
    "done": true
  },
  {
    "file_date": "2019-05-02",
    "end_date": "2019-03-31",
    "shares": 73.048943,
    "value": 37181912.0,
    "done": true
  },
  {
    "file_date": "2019-05-03",
    "end_date": "2019-03-31",
    "shares": 73.048943,
    "value": 37181912.0,
    "done": true
  },
  {
    "file_date": "2019-05-06",
    "end_date": "2019-03-31",
    "shares": 73.050589,
    "value": 37182750.0,
    "done": true
  },
  {
    "file_date": "2019-05-07",
    "end_date": "2019-03-31",
    "shares": 72.928405,
    "value": 37120558.0,
    "done": true
  },
  {
    "file_date": "2019-05-08",
    "end_date": "2019-03-31",
    "shares": 73.06912,
    "value": 37192182.0,
    "done": true
  },
  {
    "file_date": "2019-05-09",
    "end_date": "2019-03-31",
    "shares": 73.631762,
    "value": 37478567.0,
    "done": true
  },
  {
    "file_date": "2019-05-10",
    "end_date": "2019-03-31",
    "shares": 72.4456,
    "value": 36997968.0,
    "done": true
  },
  {
    "file_date": "2019-05-13",
    "end_date": "2019-03-31",
    "shares": 71.358065,
    "value": 36442564.0,
    "done": true
  },
  {
    "file_date": "2019-05-14",
    "end_date": "2019-03-31",
    "shares": 72.162614,
    "value": 36853447.0,
    "done": true
  },
  {
    "file_date": "2019-05-15",
    "end_date": "2019-03-31",
    "shares": 69.706225,
    "value": 35598969.0,
    "done": true
  },
  {
    "file_date": "2019-07-15",
    "end_date": "2019-06-30",
    "shares": 69.706225,
    "value": 35598969.0,
    "done": true
  },
  {
    "file_date": "2019-07-16",
    "end_date": "2019-06-30",
    "shares": 69.706824,
    "value": 35599275.0,
    "done": true
  },
  {
    "file_date": "2019-07-25",
    "end_date": "2019-06-30",
    "shares": 69.737261,
    "value": 35614819.0,
    "done": true
  },
  {
    "file_date": "2019-07-30",
    "end_date": "2019-06-30",
    "shares": 69.736861,
    "value": 35614615.0,
    "done": true
  },
  {
    "file_date": "2019-07-31",
    "end_date": "2019-06-30",
    "shares": 69.736861,
    "value": 35614615.0,
    "done": true
  },
  {
    "file_date": "2019-08-01",
    "end_date": "2019-06-30",
    "shares": 69.734746,
    "value": 35613535.0,
    "done": true
  },
  {
    "file_date": "2019-08-05",
    "end_date": "2019-06-30",
    "shares": 69.739037,
    "value": 35615726.0,
    "done": true
  },
  {
    "file_date": "2019-08-06",
    "end_date": "2019-06-30",
    "shares": 69.792645,
    "value": 35643104.0,
    "done": true
  },
  {
    "file_date": "2019-08-07",
    "end_date": "2019-06-30",
    "shares": 69.417394,
    "value": 35451463.0,
    "done": true
  },
  {
    "file_date": "2019-08-08",
    "end_date": "2019-06-30",
    "shares": 69.610799,
    "value": 35550235.0,
    "done": true
  },
  {
    "file_date": "2019-08-09",
    "end_date": "2019-06-30",
    "shares": 57.926711,
    "value": 35491696.0,
    "done": true
  },
  {
    "file_date": "2019-08-12",
    "end_date": "2019-06-30",
    "shares": 58.66152,
    "value": 35941913.0,
    "done": true
  },
  {
    "file_date": "2019-08-13",
    "end_date": "2019-06-30",
    "shares": 59.275262,
    "value": 36317953.0,
    "done": true
  },
  {
    "file_date": "2019-08-14",
    "end_date": "2019-06-30",
    "shares": 62.288658,
    "value": 38164261.0,
    "done": true
  },
  {
    "file_date": "2019-10-09",
    "end_date": "2019-09-30",
    "shares": 62.28866,
    "value": 38164262.0,
    "done": true
  },
  {
    "file_date": "2019-10-17",
    "end_date": "2019-09-30",
    "shares": 62.31931,
    "value": 38183041.0,
    "done": true
  },
  {
    "file_date": "2019-10-18",
    "end_date": "2019-09-30",
    "shares": 62.322306,
    "value": 38184877.0,
    "done": true
  },
  {
    "file_date": "2019-10-23",
    "end_date": "2019-09-30",
    "shares": 62.332719,
    "value": 38191257.0,
    "done": true
  },
  {
    "file_date": "2019-10-28",
    "end_date": "2019-09-30",
    "shares": 62.332719,
    "value": 38191257.0,
    "done": true
  },
  {
    "file_date": "2019-10-29",
    "end_date": "2019-09-30",
    "shares": 62.393129,
    "value": 38228270.0,
    "done": true
  },
  {
    "file_date": "2019-10-30",
    "end_date": "2019-09-30",
    "shares": 62.393129,
    "value": 38228270.0,
    "done": true
  },
  {
    "file_date": "2019-10-31",
    "end_date": "2019-09-30",
    "shares": 62.519128,
    "value": 38305470.0,
    "done": true
  },
  {
    "file_date": "2019-11-01",
    "end_date": "2019-09-30",
    "shares": 62.606723,
    "value": 38359139.0,
    "done": true
  },
  {
    "file_date": "2019-11-05",
    "end_date": "2019-09-30",
    "shares": 62.609168,
    "value": 38360637.0,
    "done": true
  },
  {
    "file_date": "2019-11-06",
    "end_date": "2019-09-30",
    "shares": 62.495717,
    "value": 38359871.0,
    "done": true
  },
  {
    "file_date": "2019-11-07",
    "end_date": "2019-09-30",
    "shares": 62.475938,
    "value": 38347731.0,
    "done": true
  },
  {
    "file_date": "2019-11-08",
    "end_date": "2019-09-30",
    "shares": 62.732002,
    "value": 38504903.0,
    "done": true
  },
  {
    "file_date": "2019-11-12",
    "end_date": "2019-09-30",
    "shares": 63.592141,
    "value": 39032856.0,
    "done": true
  },
  {
    "file_date": "2019-11-13",
    "end_date": "2019-09-30",
    "shares": 64.612854,
    "value": 39659370.0,
    "done": true
  },
  {
    "file_date": "2019-11-14",
    "end_date": "2019-09-30",
    "shares": 57.04763,
    "value": 35015835.0,
    "done": true
  },
  {
    "file_date": "2020-01-08",
    "end_date": "2019-12-31",
    "shares": 57.04763,
    "value": 35015835.0,
    "done": true
  },
  {
    "file_date": "2020-01-17",
    "end_date": "2019-12-31",
    "shares": 57.04763,
    "value": 35015835.0,
    "done": true
  },
  {
    "file_date": "2020-01-24",
    "end_date": "2019-12-31",
    "shares": 57.06558,
    "value": 35026853.0,
    "done": true
  },
  {
    "file_date": "2020-01-27",
    "end_date": "2019-12-31",
    "shares": 57.079265,
    "value": 35035253.0,
    "done": true
  },
  {
    "file_date": "2020-01-28",
    "end_date": "2019-12-31",
    "shares": 57.103703,
    "value": 35050253.0,
    "done": true
  },
  {
    "file_date": "2020-01-29",
    "end_date": "2019-12-31",
    "shares": 57.102726,
    "value": 35049653.0,
    "done": true
  },
  {
    "file_date": "2020-01-31",
    "end_date": "2019-12-31",
    "shares": 57.384446,
    "value": 35222573.0,
    "done": true
  },
  {
    "file_date": "2020-02-03",
    "end_date": "2019-12-31",
    "shares": 57.384446,
    "value": 35222573.0,
    "done": true
  },
  {
    "file_date": "2020-02-04",
    "end_date": "2019-12-31",
    "shares": 57.418587,
    "value": 35243529.0,
    "done": true
  },
  {
    "file_date": "2020-02-05",
    "end_date": "2019-12-31",
    "shares": 57.427607,
    "value": 35249065.0,
    "done": true
  },
  {
    "file_date": "2020-02-06",
    "end_date": "2019-12-31",
    "shares": 58.114687,
    "value": 35670795.0,
    "done": true
  },
  {
    "file_date": "2020-02-07",
    "end_date": "2019-12-31",
    "shares": 58.190225,
    "value": 35717160.0,
    "done": true
  },
  {
    "file_date": "2020-02-10",
    "end_date": "2019-12-31",
    "shares": 58.233068,
    "value": 35743457.0,
    "done": true
  },
  {
    "file_date": "2020-02-11",
    "end_date": "2019-12-31",
    "shares": 57.92897,
    "value": 35556802.0,
    "done": true
  },
  {
    "file_date": "2020-02-12",
    "end_date": "2019-12-31",
    "shares": 58.600995,
    "value": 35969291.0,
    "done": true
  },
  {
    "file_date": "2020-02-13",
    "end_date": "2019-12-31",
    "shares": 60.223672,
    "value": 36965290.0,
    "done": true
  },
  {
    "file_date": "2020-02-14",
    "end_date": "2019-12-31",
    "shares": 50.483139,
    "value": 30986551.0,
    "done": true
  },
  {
    "file_date": "2020-04-08",
    "end_date": "2020-03-31",
    "shares": 50.247033,
    "value": 31022518.0,
    "done": true
  },
  {
    "file_date": "2020-04-27",
    "end_date": "2020-03-31",
    "shares": 50.247033,
    "value": 31022518.0,
    "done": true
  },
  {
    "file_date": "2020-04-29",
    "end_date": "2020-03-31",
    "shares": 50.247033,
    "value": 31022518.0,
    "done": true
  },
  {
    "file_date": "2020-04-30",
    "end_date": "2020-03-31",
    "shares": 50.274582,
    "value": 31039527.0,
    "done": true
  },
  {
    "file_date": "2020-05-01",
    "end_date": "2020-03-31",
    "shares": 50.171354,
    "value": 30975794.0,
    "done": true
  },
  {
    "file_date": "2020-05-04",
    "end_date": "2020-03-31",
    "shares": 50.168486,
    "value": 30974023.0,
    "done": true
  },
  {
    "file_date": "2020-05-05",
    "end_date": "2020-03-31",
    "shares": 50.188272,
    "value": 30986239.0,
    "done": true
  },
  {
    "file_date": "2020-05-06",
    "end_date": "2020-03-31",
    "shares": 50.188273,
    "value": 30986240.0,
    "done": true
  },
  {
    "file_date": "2020-05-07",
    "end_date": "2020-03-31",
    "shares": 50.188273,
    "value": 30986240.0,
    "done": true
  },
  {
    "file_date": "2020-05-08",
    "end_date": "2020-03-31",
    "shares": 50.02351,
    "value": 30979560.0,
    "done": true
  },
  {
    "file_date": "2020-05-11",
    "end_date": "2020-03-31",
    "shares": 50.237709,
    "value": 31112213.0,
    "done": true
  },
  {
    "file_date": "2020-05-12",
    "end_date": "2020-03-31",
    "shares": 50.840289,
    "value": 31485391.0,
    "done": true
  },
  {
    "file_date": "2020-05-13",
    "end_date": "2020-03-31",
    "shares": 50.606304,
    "value": 31340484.0,
    "done": true
  },
  {
    "file_date": "2020-05-14",
    "end_date": "2020-03-31",
    "shares": 49.432036,
    "value": 30613260.0,
    "done": true
  },
  {
    "file_date": "2020-05-15",
    "end_date": "2020-03-31",
    "shares": 47.967027,
    "value": 29705980.0,
    "done": true
  },
  {
    "file_date": "2020-07-14",
    "end_date": "2020-06-30",
    "shares": 47.968217,
    "value": 29706717.0,
    "done": true
  },
  {
    "file_date": "2020-07-20",
    "end_date": "2020-06-30",
    "shares": 47.984008,
    "value": 29716496.0,
    "done": true
  },
  {
    "file_date": "2020-07-21",
    "end_date": "2020-06-30",
    "shares": 47.955768,
    "value": 29699007.0,
    "done": true
  },
  {
    "file_date": "2020-07-22",
    "end_date": "2020-06-30",
    "shares": 47.955768,
    "value": 29699007.0,
    "done": true
  },
  {
    "file_date": "2020-07-31",
    "end_date": "2020-06-30",
    "shares": 47.212517,
    "value": 29238712.0,
    "done": true
  },
  {
    "file_date": "2020-08-05",
    "end_date": "2020-06-30",
    "shares": 47.364294,
    "value": 29332707.0,
    "done": true
  },
  {
    "file_date": "2020-08-06",
    "end_date": "2020-06-30",
    "shares": 47.343058,
    "value": 29319556.0,
    "done": true
  },
  {
    "file_date": "2020-08-07",
    "end_date": "2020-06-30",
    "shares": 47.372028,
    "value": 29337497.0,
    "done": true
  },
  {
    "file_date": "2020-08-10",
    "end_date": "2020-06-30",
    "shares": 47.36979,
    "value": 29336111.0,
    "done": true
  },
  {
    "file_date": "2020-08-11",
    "end_date": "2020-06-30",
    "shares": 47.032219,
    "value": 29249337.0,
    "done": true
  },
  {
    "file_date": "2020-08-12",
    "end_date": "2020-06-30",
    "shares": 46.949188,
    "value": 29197700.0,
    "done": true
  },
  {
    "file_date": "2020-08-13",
    "end_date": "2020-06-30",
    "shares": 45.551452,
    "value": 28328448.0,
    "done": true
  },
  {
    "file_date": "2020-08-14",
    "end_date": "2020-06-30",
    "shares": 44.643129,
    "value": 27763562.0,
    "done": true
  },
  {
    "file_date": "2020-10-09",
    "end_date": "2020-09-30",
    "shares": 44.729309,
    "value": 27817157.0,
    "done": true
  },
  {
    "file_date": "2020-10-19",
    "end_date": "2020-09-30",
    "shares": 44.729309,
    "value": 27817157.0,
    "done": true
  },
  {
    "file_date": "2020-10-27",
    "end_date": "2020-09-30",
    "shares": 44.72967,
    "value": 27817382.0,
    "done": true
  },
  {
    "file_date": "2020-10-28",
    "end_date": "2020-09-30",
    "shares": 44.72967,
    "value": 27817382.0,
    "done": true
  },
  {
    "file_date": "2020-10-29",
    "end_date": "2020-09-30",
    "shares": 44.72967,
    "value": 27817382.0,
    "done": true
  },
  {
    "file_date": "2020-10-30",
    "end_date": "2020-09-30",
    "shares": 44.7453,
    "value": 27827102.0,
    "done": true
  },
  {
    "file_date": "2020-11-03",
    "end_date": "2020-09-30",
    "shares": 44.824227,
    "value": 27876187.0,
    "done": true
  },
  {
    "file_date": "2020-11-04",
    "end_date": "2020-09-30",
    "shares": 44.823169,
    "value": 27875529.0,
    "done": true
  },
  {
    "file_date": "2020-11-05",
    "end_date": "2020-09-30",
    "shares": 44.870677,
    "value": 27905074.0,
    "done": true
  },
  {
    "file_date": "2020-11-06",
    "end_date": "2020-09-30",
    "shares": 44.72501,
    "value": 28011274.0,
    "done": true
  },
  {
    "file_date": "2020-11-09",
    "end_date": "2020-09-30",
    "shares": 44.317693,
    "value": 27756171.0,
    "done": true
  },
  {
    "file_date": "2020-11-10",
    "end_date": "2020-09-30",
    "shares": 44.296946,
    "value": 27743177.0,
    "done": true
  },
  {
    "file_date": "2020-11-12",
    "end_date": "2020-09-30",
    "shares": 43.553778,
    "value": 27277731.0,
    "done": true
  },
  {
    "file_date": "2020-11-13",
    "end_date": "2020-09-30",
    "shares": 25.671934,
    "value": 16078332.0,
    "done": true
  },
  {
    "file_date": "2021-01-13",
    "end_date": "2020-12-31",
    "shares": 25.67906,
    "value": 16082795.0,
    "done": true
  },
  {
    "file_date": "2021-01-21",
    "end_date": "2020-12-31",
    "shares": 25.67906,
    "value": 16082795.0,
    "done": true
  },
  {
    "file_date": "2021-01-25",
    "end_date": "2020-12-31",
    "shares": 25.744364,
    "value": 16123695.0,
    "done": true
  },
  {
    "file_date": "2021-01-27",
    "end_date": "2020-12-31",
    "shares": 25.761731,
    "value": 16134572.0,
    "done": true
  },
  {
    "file_date": "2021-01-28",
    "end_date": "2020-12-31",
    "shares": 25.761731,
    "value": 16134572.0,
    "done": true
  },
  {
    "file_date": "2021-02-01",
    "end_date": "2020-12-31",
    "shares": 25.761731,
    "value": 16134572.0,
    "done": true
  },
  {
    "file_date": "2021-02-02",
    "end_date": "2020-12-31",
    "shares": 25.812039,
    "value": 16166080.0,
    "done": true
  },
  {
    "file_date": "2021-02-03",
    "end_date": "2020-12-31",
    "shares": 26.081284,
    "value": 16334708.0,
    "done": true
  },
  {
    "file_date": "2021-02-04",
    "end_date": "2020-12-31",
    "shares": 26.097449,
    "value": 16344832.0,
    "done": true
  },
  {
    "file_date": "2021-02-05",
    "end_date": "2020-12-31",
    "shares": 26.118379,
    "value": 16357941.0,
    "done": true
  },
  {
    "file_date": "2021-02-08",
    "end_date": "2020-12-31",
    "shares": 25.844734,
    "value": 16186557.0,
    "done": true
  },
  {
    "file_date": "2021-02-09",
    "end_date": "2020-12-31",
    "shares": 25.914547,
    "value": 16230281.0,
    "done": true
  },
  {
    "file_date": "2021-02-10",
    "end_date": "2020-12-31",
    "shares": 25.871935,
    "value": 16203593.0,
    "done": true
  },
  {
    "file_date": "2021-02-11",
    "end_date": "2020-12-31",
    "shares": 26.50214,
    "value": 16598290.0,
    "done": true
  },
  {
    "file_date": "2021-02-12",
    "end_date": "2020-12-31",
    "shares": 35.884704,
    "value": 22474590.0,
    "done": true
  },
  {
    "file_date": "2021-04-05",
    "end_date": "2021-03-31",
    "shares": 26.234344,
    "value": 22477586.0,
    "done": true
  },
  {
    "file_date": "2021-04-12",
    "end_date": "2021-03-31",
    "shares": 26.222304,
    "value": 22467270.0,
    "done": true
  },
  {
    "file_date": "2021-04-23",
    "end_date": "2021-03-31",
    "shares": 26.239577,
    "value": 22482070.0,
    "done": true
  },
  {
    "file_date": "2021-04-26",
    "end_date": "2021-03-31",
    "shares": 26.239344,
    "value": 22481870.0,
    "done": true
  },
  {
    "file_date": "2021-04-27",
    "end_date": "2021-03-31",
    "shares": 26.244947,
    "value": 22486671.0,
    "done": true
  },
  {
    "file_date": "2021-04-28",
    "end_date": "2021-03-31",
    "shares": 26.264163,
    "value": 22503135.0,
    "done": true
  },
  {
    "file_date": "2021-04-29",
    "end_date": "2021-03-31",
    "shares": 26.272499,
    "value": 22510277.0,
    "done": true
  },
  {
    "file_date": "2021-04-30",
    "end_date": "2021-03-31",
    "shares": 26.272499,
    "value": 22510277.0,
    "done": true
  },
  {
    "file_date": "2021-05-03",
    "end_date": "2021-03-31",
    "shares": 26.273721,
    "value": 22511324.0,
    "done": true
  },
  {
    "file_date": "2021-05-04",
    "end_date": "2021-03-31",
    "shares": 26.288012,
    "value": 22523569.0,
    "done": true
  },
  {
    "file_date": "2021-05-06",
    "end_date": "2021-03-31",
    "shares": 26.258396,
    "value": 22498194.0,
    "done": true
  },
  {
    "file_date": "2021-05-07",
    "end_date": "2021-03-31",
    "shares": 26.961402,
    "value": 23243425.0,
    "done": true
  },
  {
    "file_date": "2021-05-10",
    "end_date": "2021-03-31",
    "shares": 27.212176,
    "value": 23459617.0,
    "done": true
  },
  {
    "file_date": "2021-05-11",
    "end_date": "2021-03-31",
    "shares": 26.883148,
    "value": 23175962.0,
    "done": true
  },
  {
    "file_date": "2021-05-12",
    "end_date": "2021-03-31",
    "shares": 27.470126,
    "value": 23681996.0,
    "done": true
  },
  {
    "file_date": "2021-05-13",
    "end_date": "2021-03-31",
    "shares": 28.205075,
    "value": 24315595.0,
    "done": true
  },
  {
    "file_date": "2021-05-14",
    "end_date": "2021-03-31",
    "shares": 22.937572,
    "value": 19774481.0,
    "done": true
  },
  {
    "file_date": "2021-07-13",
    "end_date": "2021-06-30",
    "shares": 22.937572,
    "value": 19774481.0,
    "done": true
  },
  {
    "file_date": "2021-07-19",
    "end_date": "2021-06-30",
    "shares": 22.937572,
    "value": 19774481.0,
    "done": true
  },
  {
    "file_date": "2021-07-21",
    "end_date": "2021-06-30",
    "shares": 22.937572,
    "value": 19774481.0,
    "done": true
  },
  {
    "file_date": "2021-07-23",
    "end_date": "2021-06-30",
    "shares": 22.943372,
    "value": 19779481.0,
    "done": true
  },
  {
    "file_date": "2021-07-26",
    "end_date": "2021-06-30",
    "shares": 22.943372,
    "value": 19779481.0,
    "done": true
  },
  {
    "file_date": "2021-07-27",
    "end_date": "2021-06-30",
    "shares": 22.949172,
    "value": 19784481.0,
    "done": true
  },
  {
    "file_date": "2021-07-30",
    "end_date": "2021-06-30",
    "shares": 22.964088,
    "value": 19797340.0,
    "done": true
  },
  {
    "file_date": "2021-08-02",
    "end_date": "2021-06-30",
    "shares": 23.225623,
    "value": 20022810.0,
    "done": true
  },
  {
    "file_date": "2021-08-03",
    "end_date": "2021-06-30",
    "shares": 23.225287,
    "value": 20022520.0,
    "done": true
  },
  {
    "file_date": "2021-08-04",
    "end_date": "2021-06-30",
    "shares": 23.150171,
    "value": 19957762.0,
    "done": true
  },
  {
    "file_date": "2021-08-05",
    "end_date": "2021-06-30",
    "shares": 23.138542,
    "value": 19947737.0,
    "done": true
  },
  {
    "file_date": "2021-08-06",
    "end_date": "2021-06-30",
    "shares": 23.313898,
    "value": 20108237.0,
    "done": true
  },
  {
    "file_date": "2021-08-09",
    "end_date": "2021-06-30",
    "shares": 23.31381,
    "value": 20108161.0,
    "done": true
  },
  {
    "file_date": "2021-08-10",
    "end_date": "2021-06-30",
    "shares": 23.317319,
    "value": 20111188.0,
    "done": true
  },
  {
    "file_date": "2021-08-11",
    "end_date": "2021-06-30",
    "shares": 23.885014,
    "value": 20600825.0,
    "done": true
  },
  {
    "file_date": "2021-08-12",
    "end_date": "2021-06-30",
    "shares": 24.152494,
    "value": 20831526.0,
    "done": true
  }
]