[
  {
    "file_date": "2019-01-23",
    "end_date": "2018-12-31",
    "shares": 0.008055,
    "value": 1400,
    "done": true
  },
  {
    "file_date": "2019-02-05",
    "end_date": "2018-12-31",
    "shares": 7.100052,
    "value": 1233989,
    "done": true
  },
  {
    "file_date": "2019-02-07",
    "end_date": "2018-12-31",
    "shares": 7.102814,
    "value": 1234469,
    "done": true
  },
  {
    "file_date": "2019-02-08",
    "end_date": "2018-12-31",
    "shares": 8.464384,
    "value": 1471110,
    "done": true
  },
  {
    "file_date": "2019-02-11",
    "end_date": "2018-12-31",
    "shares": 8.51015,
    "value": 1479064,
    "done": true
  },
  {
    "file_date": "2019-02-12",
    "end_date": "2018-12-31",
    "shares": 9.080834,
    "value": 1578249,
    "done": true
  },
  {
    "file_date": "2019-02-13",
    "end_date": "2018-12-31",
    "shares": 14.187267,
    "value": 2465747,
    "done": true
  },
  {
    "file_date": "2019-02-14",
    "end_date": "2018-12-31",
    "shares": 26.15901,
    "value": 4546436,
    "done": true
  },
  {
    "file_date": "2019-02-15",
    "end_date": "2018-12-31",
    "shares": 26.164471,
    "value": 4547385,
    "done": true
  },
  {
    "file_date": "2019-03-06",
    "end_date": "2018-12-31",
    "shares": 26.164471,
    "value": 4547385,
    "done": true
  },
  {
    "file_date": "2019-04-01",
    "end_date": "2018-12-31",
    "shares": 26.164471,
    "value": 4547385,
    "done": true
  },
  {
    "file_date": "2019-04-19",
    "end_date": "2019-03-31",
    "shares": 26.164471,
    "value": 4547385,
    "done": true
  },
  {
    "file_date": "2019-04-26",
    "end_date": "2019-03-31",
    "shares": 26.164476,
    "value": 4547386,
    "done": true
  },
  {
    "file_date": "2019-05-02",
    "end_date": "2018-12-31",
    "shares": 26.164476,
    "value": 4547386,
    "done": true
  },
  {
    "file_date": "2019-05-03",
    "end_date": "2019-03-31",
    "shares": 26.68687,
    "value": 4638178,
    "done": true
  },
  {
    "file_date": "2019-05-06",
    "end_date": "2019-03-31",
    "shares": 26.686456,
    "value": 4638106,
    "done": true
  },
  {
    "file_date": "2019-05-07",
    "end_date": "2019-03-31",
    "shares": 26.685104,
    "value": 4637871,
    "done": true
  },
  {
    "file_date": "2019-05-08",
    "end_date": "2019-03-31",
    "shares": 26.692008,
    "value": 4639071,
    "done": true
  },
  {
    "file_date": "2019-05-09",
    "end_date": "2019-03-31",
    "shares": 26.656404,
    "value": 4632883,
    "done": true
  },
  {
    "file_date": "2019-05-10",
    "end_date": "2019-03-31",
    "shares": 26.656732,
    "value": 4632940,
    "done": true
  },
  {
    "file_date": "2019-05-13",
    "end_date": "2019-03-31",
    "shares": 25.515432,
    "value": 4434582,
    "done": true
  },
  {
    "file_date": "2019-05-14",
    "end_date": "2019-03-31",
    "shares": 25.567422,
    "value": 4443618,
    "done": true
  },
  {
    "file_date": "2019-05-15",
    "end_date": "2019-03-31",
    "shares": 26.65477,
    "value": 4632599,
    "done": true
  },
  {
    "file_date": "2019-07-15",
    "end_date": "2019-06-30",
    "shares": 26.69546,
    "value": 4639671,
    "done": true
  },
  {
    "file_date": "2019-07-30",
    "end_date": "2019-06-30",
    "shares": 26.699384,
    "value": 4640353,
    "done": true
  },
  {
    "file_date": "2019-08-06",
    "end_date": "2019-06-30",
    "shares": 26.663786,
    "value": 4634166,
    "done": true
  },
  {
    "file_date": "2019-08-07",
    "end_date": "2019-06-30",
    "shares": 26.656559,
    "value": 4632910,
    "done": true
  },
  {
    "file_date": "2019-08-09",
    "end_date": "2019-06-30",
    "shares": 26.656623,
    "value": 4632921,
    "done": true
  },
  {
    "file_date": "2019-08-12",
    "end_date": "2019-06-30",
    "shares": 26.653072,
    "value": 4632304,
    "done": true
  },
  {
    "file_date": "2019-08-13",
    "end_date": "2019-06-30",
    "shares": 25.3771,
    "value": 4410540,
    "done": true
  },
  {
    "file_date": "2019-08-14",
    "end_date": "2019-06-30",
    "shares": 26.188936,
    "value": 4551637,
    "done": true
  },
  {
    "file_date": "2019-08-15",
    "end_date": "2019-06-30",
    "shares": 27.025219,
    "value": 4696983,
    "done": true
  },
  {
    "file_date": "2019-08-23",
    "end_date": "2019-06-30",
    "shares": 26.548861,
    "value": 4614192.0,
    "done": true
  },
  {
    "file_date": "2019-10-21",
    "end_date": "2019-09-30",
    "shares": 26.548861,
    "value": 4614192.0,
    "done": true
  },
  {
    "file_date": "2019-11-05",
    "end_date": "2019-09-30",
    "shares": 26.529321,
    "value": 4610796.0,
    "done": true
  },
  {
    "file_date": "2019-11-07",
    "end_date": "2019-09-30",
    "shares": 26.529321,
    "value": 4610796.0,
    "done": true
  },
  {
    "file_date": "2019-11-08",
    "end_date": "2019-09-30",
    "shares": 26.522992,
    "value": 4609696.0,
    "done": true
  },
  {
    "file_date": "2019-11-12",
    "end_date": "2019-09-30",
    "shares": 29.982348,
    "value": 5210932.0,
    "done": true
  },
  {
    "file_date": "2019-11-13",
    "end_date": "2019-09-30",
    "shares": 30.120955,
    "value": 5235022.0,
    "done": true
  },
  {
    "file_date": "2019-11-14",
    "end_date": "2019-09-30",
    "shares": 28.556623,
    "value": 4963141.0,
    "done": true
  },
  {
    "file_date": "2019-11-19",
    "end_date": "2019-09-30",
    "shares": 26.920673,
    "value": 4678813.0,
    "done": true
  },
  {
    "file_date": "2020-01-10",
    "end_date": "2019-12-31",
    "shares": 26.952894,
    "value": 4684413.0,
    "done": true
  },
  {
    "file_date": "2020-01-29",
    "end_date": "2019-12-31",
    "shares": 26.952894,
    "value": 4684413.0,
    "done": true
  },
  {
    "file_date": "2020-02-04",
    "end_date": "2019-12-31",
    "shares": 27.96607,
    "value": 4860503.0,
    "done": true
  },
  {
    "file_date": "2020-02-06",
    "end_date": "2019-12-31",
    "shares": 27.899333,
    "value": 4848904.0,
    "done": true
  },
  {
    "file_date": "2020-02-07",
    "end_date": "2019-12-31",
    "shares": 27.9329,
    "value": 4854738.0,
    "done": true
  },
  {
    "file_date": "2020-02-11",
    "end_date": "2019-12-31",
    "shares": 27.9329,
    "value": 4854738.0,
    "done": true
  },
  {
    "file_date": "2020-02-12",
    "end_date": "2019-12-31",
    "shares": 27.929298,
    "value": 4854112.0,
    "done": true
  },
  {
    "file_date": "2020-02-13",
    "end_date": "2019-12-31",
    "shares": 28.174264,
    "value": 4896687.0,
    "done": true
  },
  {
    "file_date": "2020-02-14",
    "end_date": "2019-12-31",
    "shares": 30.177946,
    "value": 5244927.0,
    "done": true
  },
  {
    "file_date": "2020-04-20",
    "end_date": "2020-03-31",
    "shares": 29.766896,
    "value": 5244927.0,
    "done": true
  },
  {
    "file_date": "2020-04-28",
    "end_date": "2020-03-31",
    "shares": 29.772571,
    "value": 5245927.0,
    "done": true
  },
  {
    "file_date": "2020-05-01",
    "end_date": "2020-03-31",
    "shares": 29.771617,
    "value": 5245759.0,
    "done": true
  },
  {
    "file_date": "2020-05-04",
    "end_date": "2020-03-31",
    "shares": 29.569086,
    "value": 5210073.0,
    "done": true
  },
  {
    "file_date": "2020-05-12",
    "end_date": "2020-03-31",
    "shares": 29.569086,
    "value": 5210073.0,
    "done": true
  },
  {
    "file_date": "2020-05-13",
    "end_date": "2020-03-31",
    "shares": 29.569086,
    "value": 5210073.0,
    "done": true
  },
  {
    "file_date": "2020-05-14",
    "end_date": "2020-03-31",
    "shares": 29.660045,
    "value": 5243896.0,
    "done": true
  },
  {
    "file_date": "2020-05-15",
    "end_date": "2020-03-31",
    "shares": 29.301929,
    "value": 5180581.0,
    "done": true
  },
  {
    "file_date": "2020-05-26",
    "end_date": "2020-03-31",
    "shares": 29.301929,
    "value": 5180581.0,
    "done": true
  },
  {
    "file_date": "2020-06-16",
    "end_date": "2020-03-31",
    "shares": 23.247059,
    "value": 4110080.0,
    "done": true
  },
  {
    "file_date": "2020-07-22",
    "end_date": "2020-06-30",
    "shares": 23.247059,
    "value": 4110080.0,
    "done": true
  },
  {
    "file_date": "2020-07-31",
    "end_date": "2020-06-30",
    "shares": 23.253365,
    "value": 4111195.0,
    "done": true
  },
  {
    "file_date": "2020-08-03",
    "end_date": "2020-06-30",
    "shares": 23.253365,
    "value": 4111195.0,
    "done": true
  },
  {
    "file_date": "2020-08-06",
    "end_date": "2020-06-30",
    "shares": 23.253207,
    "value": 4111167.0,
    "done": true
  },
  {
    "file_date": "2020-08-07",
    "end_date": "2020-06-30",
    "shares": 20.597568,
    "value": 3641650.0,
    "done": true
  },
  {
    "file_date": "2020-08-11",
    "end_date": "2020-06-30",
    "shares": 20.503298,
    "value": 3624983.0,
    "done": true
  },
  {
    "file_date": "2020-08-12",
    "end_date": "2020-06-30",
    "shares": 20.154689,
    "value": 3563349.0,
    "done": true
  },
  {
    "file_date": "2020-08-13",
    "end_date": "2020-06-30",
    "shares": 17.84013,
    "value": 3436009.0,
    "done": true
  },
  {
    "file_date": "2020-08-14",
    "end_date": "2020-06-30",
    "shares": 18.337046,
    "value": 3531715.0,
    "done": true
  },
  {
    "file_date": "2020-08-17",
    "end_date": "2020-06-30",
    "shares": 18.621054,
    "value": 3586415.0,
    "done": true
  },
  {
    "file_date": "2020-08-24",
    "end_date": "2020-06-30",
    "shares": 18.621054,
    "value": 3586415.0,
    "done": true
  },
  {
    "file_date": "2020-08-31",
    "end_date": "2020-06-30",
    "shares": 18.621054,
    "value": 3586415.0,
    "done": true
  },
  {
    "file_date": "2020-11-05",
    "end_date": "2020-09-30",
    "shares": 18.842575,
    "value": 3629080.0,
    "done": true
  },
  {
    "file_date": "2020-11-06",
    "end_date": "2020-09-30",
    "shares": 18.856464,
    "value": 3631755.0,
    "done": true
  },
  {
    "file_date": "2020-11-09",
    "end_date": "2020-09-30",
    "shares": 22.421563,
    "value": 4318393.0,
    "done": true
  },
  {
    "file_date": "2020-11-10",
    "end_date": "2020-09-30",
    "shares": 22.424128,
    "value": 4318887.0,
    "done": true
  },
  {
    "file_date": "2020-11-12",
    "end_date": "2020-09-30",
    "shares": 20.875916,
    "value": 5162614.0,
    "done": true
  },
  {
    "file_date": "2020-11-13",
    "end_date": "2020-09-30",
    "shares": 20.437157,
    "value": 5054109.0,
    "done": true
  },
  {
    "file_date": "2020-11-16",
    "end_date": "2020-09-30",
    "shares": 33.596276,
    "value": 8308359.0,
    "done": true
  },
  {
    "file_date": "2021-01-14",
    "end_date": "2020-12-31",
    "shares": 33.703837,
    "value": 8334959.0,
    "done": true
  },
  {
    "file_date": "2021-02-01",
    "end_date": "2020-12-31",
    "shares": 33.240538,
    "value": 8220385.0,
    "done": true
  },
  {
    "file_date": "2021-02-02",
    "end_date": "2020-12-31",
    "shares": 33.237262,
    "value": 8219575.0,
    "done": true
  },
  {
    "file_date": "2021-02-04",
    "end_date": "2020-12-31",
    "shares": 33.237359,
    "value": 8219599.0,
    "done": true
  },
  {
    "file_date": "2021-02-05",
    "end_date": "2020-12-31",
    "shares": 33.429911,
    "value": 8267217.0,
    "done": true
  },
  {
    "file_date": "2021-02-08",
    "end_date": "2020-12-31",
    "shares": 33.429911,
    "value": 8267217.0,
    "done": true
  },
  {
    "file_date": "2021-02-09",
    "end_date": "2020-12-31",
    "shares": 33.491646,
    "value": 8282484.0,
    "done": true
  },
  {
    "file_date": "2021-02-10",
    "end_date": "2020-12-31",
    "shares": 33.302738,
    "value": 8235767.0,
    "done": true
  },
  {
    "file_date": "2021-02-11",
    "end_date": "2020-12-31",
    "shares": 33.539854,
    "value": 8294406.0,
    "done": true
  },
  {
    "file_date": "2021-02-12",
    "end_date": "2020-12-31",
    "shares": 31.553118,
    "value": 7803086.0,
    "done": true
  },
  {
    "file_date": "2021-02-16",
    "end_date": "2020-12-31",
    "shares": 34.737351,
    "value": 8590547.0,
    "done": true
  },
  {
    "file_date": "2021-02-17",
    "end_date": "2020-12-31",
    "shares": 34.823199,
    "value": 8611777.0,
    "done": true
  },
  {
    "file_date": "2021-02-24",
    "end_date": "2020-12-31",
    "shares": 34.896983,
    "value": 8630024.0,
    "done": true
  },
  {
    "file_date": "2021-02-25",
    "end_date": "2020-12-31",
    "shares": 34.453259,
    "value": 8520291.0,
    "done": true
  },
  {
    "file_date": "2021-04-28",
    "end_date": "2021-03-31",
    "shares": 29.339845,
    "value": 8520291.0,
    "done": true
  },
  {
    "file_date": "2021-04-29",
    "end_date": "2021-03-31",
    "shares": 29.310231,
    "value": 8511691.0,
    "done": true
  },
  {
    "file_date": "2021-05-04",
    "end_date": "2021-03-31",
    "shares": 31.476632,
    "value": 9140814.0,
    "done": true
  },
  {
    "file_date": "2021-05-07",
    "end_date": "2021-03-31",
    "shares": 31.350152,
    "value": 9104084.0,
    "done": true
  },
  {
    "file_date": "2021-05-12",
    "end_date": "2021-03-31",
    "shares": 31.523299,
    "value": 9154366.0,
    "done": true
  },
  {
    "file_date": "2021-05-13",
    "end_date": "2021-03-31",
    "shares": 32.732073,
    "value": 9505394.0,
    "done": true
  },
  {
    "file_date": "2021-05-14",
    "end_date": "2021-03-31",
    "shares": 32.94677,
    "value": 9567742.0,
    "done": true
  },
  {
    "file_date": "2021-05-17",
    "end_date": "2021-03-31",
    "shares": 33.746525,
    "value": 9799991.0,
    "done": true
  },
  {
    "file_date": "2021-05-18",
    "end_date": "2021-03-31",
    "shares": 32.679439,
    "value": 9490109.0,
    "done": true
  },
  {
    "file_date": "2021-05-21",
    "end_date": "2021-03-31",
    "shares": 32.679439,
    "value": 9490109.0,
    "done": true
  },
  {
    "file_date": "2021-07-20",
    "end_date": "2021-03-31",
    "shares": 27.152875,
    "value": 7885195.0,
    "done": true
  },
  {
    "file_date": "2021-07-29",
    "end_date": "2021-06-30",
    "shares": 27.153908,
    "value": 7885495.0,
    "done": true
  },
  {
    "file_date": "2021-08-03",
    "end_date": "2021-06-30",
    "shares": 27.250386,
    "value": 7913512.0,
    "done": true
  },
  {
    "file_date": "2021-08-05",
    "end_date": "2021-06-30",
    "shares": 27.250386,
    "value": 7913512.0,
    "done": true
  },
  {
    "file_date": "2021-08-10",
    "end_date": "2021-06-30",
    "shares": 27.25073,
    "value": 7913612.0,
    "done": true
  },
  {
    "file_date": "2021-08-11",
    "end_date": "2021-06-30",
    "shares": 26.994847,
    "value": 7931086.0,
    "done": true
  },
  {
    "file_date": "2021-08-13",
    "end_date": "2021-06-30",
    "shares": 28.704833,
    "value": 8433480.0,
    "done": true
  },
  {
    "file_date": "2021-08-16",
    "end_date": "2021-06-30",
    "shares": 28.865082,
    "value": 8480561.0,
    "done": true
  },
  {
    "file_date": "2021-08-17",
    "end_date": "2021-06-30",
    "shares": 28.775813,
    "value": 8454334.0,
    "done": true
  },
  {
    "file_date": "2021-08-23",
    "end_date": "2021-06-30",
    "shares": 28.775813,
    "value": 8454334.0,
    "done": true
  },
  {
    "file_date": "2021-09-13",
    "end_date": "2021-06-30",
    "shares": 28.775813,
    "value": 8454334.0,
    "done": true
  }
]